{
  "status": "ok",
  "totalResults": 34,
  "articles": [
    {
      "source": { "id": null, "name": "Yahoo Entertainment" },
      "author": "Yahoo奇摩（即時新聞）",
      "title": "嘉縣葫蘆谷溪水暴漲 17名遊客受困已陸續協助脱困 - Yahoo奇摩新聞",
      "description": "嘉縣番路葫蘆谷大雨 10餘遊客雨受困溪谷救援中",
      "url": "https://tw.news.yahoo.com/%E5%98%89%E7%B8%A3%E7%95%AA%E8%B7%AF%E8%91%AB%E8%98%86%E8%B0%B7%E5%A4%A7%E9%9B%A8-10-%E9%A4%98%E9%81%8A%E5%AE%A2%E9%9B%A8%E5%8F%97%E5%9B%B0%E6%BA%AA%E8%B0%B7%E6%95%91%E6%8F%B4%E4%B8%AD-102000947.html",
      "urlToImage": "https://s.yimg.com/os/creatr-uploaded-images/2022-08/2dd4c760-1644-11ed-ad57-7d2d42be7b62",
      "publishedAt": "2022-08-07T12:27:03Z",
      "content": "Antony Blinken6Ferdinand \"Bongbong\" Marcos Jr.Nancy Pelosi14"
    },
    {
      "source": { "id": null, "name": "Setn.com" },
      "author": "三立新聞網",
      "title": "《世紀帝國4》疑標錯價還沒改！台灣是「全世界最低價」 - 三立新聞網 Setn.com",
      "description": "微軟旗下即時戰略遊戲《世紀帝國4》從昨（6）日開始在Steam平台及自家的Windows商城大特價，原價1,499元下殺1.7折，258元就能輕鬆入手，數位豪華版也僅要348元，截至目前仍未修改價錢。",
      "url": "https://www.setn.com/News.aspx?NewsID=1158158",
      "urlToImage": "https://attach.setn.com/newsimages/2022/08/07/3769417-PH.jpg",
      "publishedAt": "2022-08-07T11:52:00Z",
      "content": "4Steam\r\n46SteamWindows1,4991.7258348\r\n4Steam\r\nSteamDB7.541.7\r\nSteam\r\n20"
    },
    {
      "source": { "id": null, "name": "Gamereactor.cn" },
      "author": null,
      "title": "Unrailed - 遊戲玩法 - Gamereactor China",
      "description": "我們玩了Epic Games Store本周提供的免費遊戲，其中我們將不得不嘗試構建火車軌道，因為它遵循其路線並試圖到達目的地。然而，我們必須與時間賽跑，才能獲得必要的資源來建造這些軌道，這項任務不僅取決於我們，還取決於我們的其他三個同伴，如果我們不想讓火車最終被摧毀，我們將不得不與他們一起工作......你能把這列火車和它的乘客送到一個安全的目的地嗎？",
      "url": "https://www.gamereactor.cn/grtv/613403/Unrailed+%E9%81%8A%E6%88%B2%E7%8E%A9%E6%B3%95/",
      "urlToImage": "https://www.gamereactor.cn/media/grtv/34/613403_w926.jpg",
      "publishedAt": "2022-08-07T11:51:32Z",
      "content": "Gamereactor . Gamereactor cookies cookies\r\nOK"
    },
    {
      "source": { "id": null, "name": "Gamereactor.cn" },
      "author": null,
      "title": "Hard West 2 - 直播重播 - Gamereactor China",
      "description": "我想我們都同意，當我們玩回合制戰略遊戲時，我們正在尋找一個好的戰略挑戰和一個好的故事來支援戰鬥系統......而這正是Hard West 2所提供的，因為它為我們提供了我們最熟悉的狂野西部的典型決鬥和戰鬥場景，具有超自然的特徵和從未見過的觀點。事實是，經過一個小時的遊戲，我們可以毫無疑問地說，這款遊戲的戰鬥機制和神秘的故事都讓我們眼花繚亂。",
      "url": "https://www.gamereactor.cn/grtv/613393/Hard+West+2+%E7%9B%B4%E6%92%AD%E9%87%8D%E6%92%AD/",
      "urlToImage": "https://www.gamereactor.cn/media/grtv/33/613393_w926.jpg",
      "publishedAt": "2022-08-07T11:45:04Z",
      "content": "Gamereactor . Gamereactor cookies cookies\r\nOK"
    },
    {
      "source": { "id": null, "name": "udn 聯合新聞網" },
      "author": "記者蘇志畬／台南即時報導",
      "title": "U12世界盃／吳聖智、陳瑞鑫開轟 中華隊奪季軍 - udn.com",
      "description": "U12世界盃少棒賽季軍戰今天下午開打，中華隊對多明尼加隊，比賽一度因雨中斷2個半小時，但中華隊不受影響，仍以9：5擊敗對...",
      "url": "https://udn.com/news/story/7001/6519634",
      "urlToImage": "https://pgw.udn.com.tw/gw/photo.php?u=https://uc.udn.com.tw/photo/2022/08/07/realtime/18233210.jpeg&s=Y&x=0&y=0&sw=1280&sh=853&exp=3600",
      "publishedAt": "2022-08-07T10:51:18Z",
      "content": null
    },
    {
      "source": { "id": null, "name": "Appledaily.com.tw" },
      "author": "蘋果新聞網",
      "title": "張善為神隱9年今47歲生日粉絲po文「我們一直都在」惹鼻酸｜蘋果新聞網｜蘋果日報 - 蘋果新聞網",
      "description": "「黑皮哥哥」張善為，2013年血塊壓迫脊椎神經住院開刀，下身癱瘓，消失螢光幕已9年。今（7日）張善為過47歲生日，想念他的粉絲，在臉書發祝賀影片，祝福他生日快樂，「我們真的想你了⋯那些年的小小孩都長大了」，並暖心喊話「我們其實一直都在」。&nbsp;12年前，曾與他合作客家戲劇的吳政迪，今也在臉書發文，嘆「想你，希望你一切都好！我也都好好的，你放心」。",
      "url": "https://www.appledaily.com.tw/entertainment/20220807/1830A77B7F0C96101BCC700110",
      "urlToImage": "https://static.appledaily.com.tw/prod/2022-08/1830A77B7F0C96101BCC700110/563b3d762d065df79eec3ebf2977d61e_large.jpg",
      "publishedAt": "2022-08-07T10:32:00Z",
      "content": null
    },
    {
      "source": { "id": null, "name": "Gamereactor.cn" },
      "author": "Ben Lyons",
      "title": "華碩ROG流量 X16 - Gamereactor China",
      "description": "這款 2 合 1 遊戲筆記型電腦專為工作和娛樂而設計。",
      "url": "https://www.gamereactor.cn/gadgets/343153/%E8%8F%AF%E7%A2%A9ROG%E6%B5%81%E9%87%8F+X16/",
      "urlToImage": "https://www.gamereactor.cn/media/37/asusrogflow_3833763b.png",
      "publishedAt": "2022-08-07T10:29:30Z",
      "content": "ROGROG Flow X16\r\nFlow X16AMD Ryzen 9 6900HSNvidia GeForce RTX 3070 Ti32GBDDR5 RAM4800MHz70Forza Horizon 572fpsTurbo82fps\r\nQHD2K1440pHDRFlow X16165Hz\r\n360As Dusk FallsROG Zephyrus DuoFlow X1621\r\nROGFl… [+140 chars]"
    },
    {
      "source": { "id": null, "name": "Ltn.com.tw" },
      "author": "自由時報",
      "title": "共軍實彈射擊結束 外籍航空航班已陸續恢復 - 自由時報",
      "description": "中共解放軍4日起在台灣周邊海域舉行實彈演習至今天中午。而中國發布1到6個臨時危險區飛航公告今天中午12時失效，第7區明天上午10時失效。原本這兩天取消外籍航空航班陸續恢復正常。美國眾議院議長裴洛西8月2日晚間至3日傍晚訪台，中國宣布共軍4日中午12時至7日中午12時，在台灣附近6個海域「進行重要軍事演訓行動，並組織實彈射擊」。航港局4日上午再發布新的航船布告，其中提到中共解放軍的軍演區域多了1處，在東部海域。",
      "url": "https://news.ltn.com.tw/news/politics/breakingnews/4017634",
      "urlToImage": "https://img.ltn.com.tw/Upload/news/600/2022/08/07/php4Ha236.jpg",
      "publishedAt": "2022-08-07T10:06:53Z",
      "content": null
    },
    {
      "source": { "id": null, "name": "Appledaily.com.tw" },
      "author": "蘋果新聞網",
      "title": "軍演3天沒完沒了！共軍今宣布「繼續對台灣實戰演訓」 檢驗聯合火力｜蘋果新聞網｜蘋果日報 - 蘋果新聞網",
      "description": "中國解放軍從4日開始大動作舉行 3 天的實彈軍演，而東部戰區按計劃預計是今天（7日）中午12點會結束演習，但是稍早微博「東部戰區」發出快訊表示，「8月7日，中國人民解放軍東部戰區按計劃，繼續位台灣周邊海空域進行實戰化聯合演訓，重點檢驗聯合火力對地打擊和遠距離空中打擊能力」。",
      "url": "https://www.appledaily.com.tw/politics/20220807/253DB510691B1C30237B826459",
      "urlToImage": "https://static.appledaily.com.tw/prod/2022-08/253DB510691B1C30237B826459/5a421a64ce4f93043abbd8137b5828ad_large.jpg",
      "publishedAt": "2022-08-07T10:02:19Z",
      "content": null
    },
    {
      "source": { "id": null, "name": "Ettoday.net" },
      "author": "ETtoday新聞雲",
      "title": "南華早報：北京對美日宣洩怒氣後 外交面臨兩難 - ETtoday新聞雲",
      "description": "美國眾議院議長裴洛西（Nancy Pelosi）訪台後，中方透過軍事演習展示武力，也對美日兩國宣洩怒氣。分析指出，這對北京政府來說，似乎是加大外交賭注，如今處於兩難困境之中，到底該讓事態進一步升級，或是努力與其他鄰國站在同一陣線，以避免各國疏離。(第四次台海危機,南華早報,軍演)",
      "url": "https://www.ettoday.net/news/20220807/2311244.htm",
      "urlToImage": "https://cdn2.ettoday.net/images/6497/d6497245.jpg",
      "publishedAt": "2022-08-07T09:46:00Z",
      "content": "8\r\nNancy Pelosi\r\n7\r\nSourabh Gupta\r\n4\r\nLa Trobe UniversityNick Bisley\r\nAntony Blinken\r\nLu Xiang\r\nLi Mingjiang"
    },
    {
      "source": { "id": null, "name": "Yahoo Entertainment" },
      "author": "李靖棠",
      "title": "王心凌奪《浪姐3》總冠軍人氣飆 再獲2陸綜邀請 - Yahoo奇摩新聞",
      "description": "湖南衛視芒果台的《乘風破浪》第三季5日正式落幕，台灣歌手王心凌也榮獲最高票奪得總冠軍頭銜，繼冠軍之後、王心凌未來動向也備受關注，從她個人微博更新終能發現，繼《乘風破浪》第三季後，甜心教主再獲兩個綜藝節目邀請加盟，而隨著曝光度與人氣暴漲，也讓王心凌微博粉絲人數飆破730萬。",
      "url": "https://tw.news.yahoo.com/%E5%A5%AA-%E6%B5%AA%E5%A7%903-%E7%B8%BD%E5%86%A0%E8%BB%8D%E5%86%8D%E7%8D%B2%E9%99%B8%E7%B6%9C%E9%82%80%E8%AB%8B-%E7%8E%8B%E5%BF%83%E5%87%8C%E5%BE%AE%E5%8D%9A%E7%B2%89%E9%A3%86%E7%A0%B4700%E8%90%AC-084514239.html",
      "urlToImage": "https://s.yimg.com/uu/api/res/1.2/N6I.vsEYTbyZtb3_LFv3zg--~B/aD01OTY7dz0xMDYwO2FwcGlkPXl0YWNoeW9u/https://media.zenfs.com/zh-tw/news_tvbs_com_tw_938/5d06aa57250fbd06ba2104e61baf1f40",
      "publishedAt": "2022-08-07T09:18:54Z",
      "content": "James KarinchakJose AltuveJames Karinchak, Nasty 83mph Curveball...and Psycho K Strut. ? pic.twitter.com/RxTlxIBfar Rob Friedman (@PitchingNinja) August 7, 2022 2683mph412231.981.02WHIPJames Karincha… [+17 chars]"
    },
    {
      "source": { "id": null, "name": "Yahoo Entertainment" },
      "author": "東森新聞",
      "title": "台海局勢緊繃！推特創辦人突喊「滅共宣言」 萬人看呆 - Yahoo奇摩新聞",
      "description": "近日共軍正在進行實彈軍演，台海局勢相當緊張，想不到就在這敏感時機點，推特創辦人杜錫（Jack Dorsey）突然發表了三個字的「滅共宣言」，讓所有人都看呆了。 美國眾院議長裴洛西",
      "url": "https://tw.news.yahoo.com/%E5%8F%B0%E6%B5%B7%E5%B1%80%E5%8B%A2%E7%B7%8A%E7%B9%83-%E6%8E%A8%E7%89%B9%E5%89%B5%E8%BE%A6%E4%BA%BA%E7%AA%81%E5%96%8A-%E6%BB%85%E5%85%B1%E5%AE%A3%E8%A8%80-%E8%90%AC%E4%BA%BA%E7%9C%8B%E5%91%86-085900109.html",
      "urlToImage": "https://s.yimg.com/uu/api/res/1.2/WSv_e7jm.0KpbUoZ.rE10g--~B/aD02NzU7dz0xMjAwO2FwcGlkPXl0YWNoeW9u/https://media.zenfs.com/en/ebc.net.tw/c191dee4278b224ae19eb4803cd24233",
      "publishedAt": "2022-08-07T08:59:00Z",
      "content": "[newtalk] Nancy PelosiThe Korea Times Institute for China-American Studies, ICASSourabh Gupta"
    },
    {
      "source": { "id": null, "name": "Ltn.com.tw" },
      "author": "自由時報",
      "title": "中職》「練一練搞不好160吧！」高國慶建議宋晟睿趁早二刀流 - 自由時報",
      "description": "43歲的統一獅大學長高國慶昨天遭中信兄弟19歲小老弟宋晟睿三振，他今天賽前先是笑說：「個人造業還是要還。」畢竟他過去「登板」時也曾飆出三振，隨即又讚嘆起宋晟睿的火球功，「這小朋友再練一練，搞不好160吧！」高國慶昨在8下擔任首名打者，就遇上宋晟睿的生涯初登板，「第1顆就145，我還問捕手他已經催了嗎",
      "url": "https://sports.ltn.com.tw/news/breakingnews/4017562",
      "urlToImage": "https://img.ltn.com.tw/Upload/sports/page/800S/2022/08/07/phpwBxVZd.jpg",
      "publishedAt": "2022-08-07T08:21:00Z",
      "content": "© 2022 The Liberty Times. All Rights Reserved."
    },
    {
      "source": { "id": null, "name": "udn 聯合新聞網" },
      "author": "記者林佳彣／宜蘭即時報導",
      "title": "頭城外海傳遊艇翻覆 12人落海救起無大礙 - udn.com",
      "description": "宜蘭縣頭城外海今天下午3點多發生船隻翻覆意外。據悉，事發地點為頭城鎮大里漁港1海浬處，一艘自用遊艇不明原因翻覆，海巡獲報...",
      "url": "https://udn.com/news/story/7320/6519367",
      "urlToImage": "https://pgw.udn.com.tw/gw/photo.php?u=https://uc.udn.com.tw/photo/2022/08/07/1/18232117.jpg&s=Y&x=0&y=0&sw=1280&sh=853&exp=3600",
      "publishedAt": "2022-08-07T07:44:08Z",
      "content": null
    },
    {
      "source": { "id": null, "name": "Soundofhope.org" },
      "author": null,
      "title": "出汗多≠排毒，傷腎又毀顏！這3個方法收火氣 - SOH_NEWS_CN",
      "description": "夏天，一個必須流汗的季節。但夏季就是要出汗，天越熱，咱們就越要享受炎熱，讓自己的心陽旺盛，把汗透出來。如此，那些郁滯於體內的風寒濕邪，才能一一排出。",
      "url": "https://www.soundofhope.org/post/643133?lang=b5",
      "urlToImage": "https://img.soundofhope.org/2020-05/1590243712429.gif",
      "publishedAt": "2022-08-07T07:38:33Z",
      "content": null
    },
    {
      "source": { "id": null, "name": "Ettoday.net" },
      "author": "ETtoday新聞雲",
      "title": "怕被台海危機波及！菲律賓急擬撤僑計畫 美承諾將保障盟友安全 - ETtoday新聞雲",
      "description": "美國國務卿布林肯6日向菲律賓總統小馬可仕保證，若菲律賓在南海受到攻擊，美國將遵守承諾，援引《美菲共同防御條約》出手協防。儘管小馬可仕表示，他不認為裴洛西訪台讓台海局勢惡化，不過有外媒透露，馬尼拉經濟文化辦事處已著手研擬撤僑計畫，以確保菲律賓能在台海戰爭爆發時，及時撤離在台僑民。(軍武,國際軍武,美國,北美要聞,中國,大陸軍武,美中關係,台灣,中共環台軍演,第四次台海危機,菲律賓,東南亞要聞,撤僑)",
      "url": "https://www.ettoday.net/news/20220807/2311099.htm",
      "urlToImage": "https://cdn2.ettoday.net/images/6496/d6496916.jpg",
      "publishedAt": "2022-08-07T06:50:00Z",
      "content": "6\r\nAntony Blinken6Ferdinand Marcos Jr.\r\nCNNRodrigo Duterte2022\r\n6701951\r\nEnrique ManaloMECO614"
    },
    {
      "source": { "id": null, "name": "Chinatimes.com" },
      "author": "吳映璠",
      "title": "英媒揭陸奪台4劇本 避免俄大錯恐爆48小時閃電戰 - 中時新聞網 Chinatimes.com",
      "description": "英國《每日電訊報》（Daily Telegraph）6日引述外交消息人士指出，中國大陸從俄羅斯入侵烏克蘭的戰爭中學到教訓，最快可能在2023年對台灣發動48小時的閃電戰，可能依照4種情境奪下台灣，包括封鎖台灣、入侵馬祖及金",
      "url": "https://www.chinatimes.com/realtimenews/20220807001970-260408",
      "urlToImage": "https://images.chinatimes.com/newsphoto/2022-08-07/656/20220807002074.jpg",
      "publishedAt": "2022-08-07T06:30:43Z",
      "content": "2 Invade the Matsu and Kinmen islands\r\nThe islands, some of which lie less than 10km from Chinas mainland\r\nAs a show of strength and to test Western resolve, Beijing could invade some or all of the i… [+124 chars]"
    },
    {
      "source": { "id": null, "name": "Ettoday.net" },
      "author": "ETtoday新聞雲",
      "title": "獨／草屯4死血案倖存者醒了！賴敏男父親節前順利拔管「自主呼吸」 - ETtoday新聞雲",
      "description": "南投縣草屯康建生技公司7月驚爆4死血案，唯一倖存的康建創辦人賴敏男昏迷半個多月後，已經在8月初順利拔管，能夠自主呼吸。據悉，賴敏男現在雖已清醒，與人簡單互動、點頭，卻還無法說話，於自己身在何處仍相當混亂，但每天都在進步中。(康健,賴敏男)",
      "url": "https://www.ettoday.net/news/20220807/2311123.htm",
      "urlToImage": "https://cdn2.ettoday.net/images/6459/d6459435.jpg",
      "publishedAt": "2022-08-07T05:58:00Z",
      "content": null
    },
    {
      "source": { "id": null, "name": "Yahoo Entertainment" },
      "author": "賴意文",
      "title": "張育成開轟也挨轟 教頭感謝願意投球 - Yahoo奇摩運動",
      "description": "張育成今天不僅轟出來到光芒後的第1支全壘打，還首度踏上職業比賽的投手丘。",
      "url": "https://tw.sports.yahoo.com/news/%E5%BC%B5%E8%82%B2%E6%88%90%E9%96%8B%E8%BD%9F%E4%B9%9F%E6%8C%A8%E8%BD%9F-%E6%95%99%E9%A0%AD%E6%84%9F%E8%AC%9D%E9%A1%98%E6%84%8F%E6%8A%95%E7%90%83-052531121.html",
      "urlToImage": "https://s.yimg.com/ny/api/res/1.2/p_HwMYBbE_yTMxy9kVU5ZA--/YXBwaWQ9aGlnaGxhbmRlcjt3PTEyMDA7aD04MDA-/https://s.yimg.com/os/creatr-uploaded-images/2022-08/414a2560-1626-11ed-97cf-40a1b5191513",
      "publishedAt": "2022-08-07T05:46:21Z",
      "content": "Thomas LO /Mandiri Indonesia OpenGaganjeet Bhu"
    },
    {
      "source": { "id": null, "name": "udn 聯合新聞網" },
      "author": "記者鄒尚謙／台北即時報導",
      "title": "rTMS治療咀嚼吞嚥障礙醫：中風患者成功移除鼻胃管｜元氣網 - udn 元氣網",
      "description": "台灣咀嚼吞嚥障礙醫學會今舉行實體研討會，理事長王亭貴表示，咀嚼吞嚥障礙的患者在社區內很常見，但由於民眾衛教不足，就醫時大部分都已有",
      "url": "https://health.udn.com/health/story/5967/6518958",
      "urlToImage": "https://pgw.udn.com.tw/gw/photo.php?u=https://uc.udn.com.tw/photo/2022/08/07/realtime/18230903.jpg&x=23&y=0&sw=1002&sh=669&s=Y&exp=3600",
      "publishedAt": "2022-08-07T04:43:16Z",
      "content": null
    },
    {
      "source": { "id": null, "name": "Ltn.com.tw" },
      "author": "自由時報",
      "title": "共軍實彈射擊結束 外籍航空航班已陸續恢復 - 自由時報",
      "description": "中共解放軍4日起在台灣周邊海域舉行實彈演習至今天中午。而中國發布1到6個臨時危險區飛航公告今天中午12時失效，第7區明天上午10時失效。原本這兩天取消外籍航空航班陸續恢復正常。美國眾議院議長裴洛西8月2日晚間至3日傍晚訪台，中國宣布共軍4日中午12時至7日中午12時，在台灣附近6個海域「進行重要軍事演訓行動，並組織實彈射擊」。航港局4日上午再發布新的航船布告，其中提到中共解放軍的軍演區域多了1處，在東部海域。",
      "url": "https://news.ltn.com.tw/news/politics/breakingnews/4017634",
      "urlToImage": "https://img.ltn.com.tw/Upload/news/600/2022/08/07/php4Ha236.jpg",
      "publishedAt": "2022-08-07T10:06:53Z",
      "content": null
    },
    {
      "source": { "id": null, "name": "Appledaily.com.tw" },
      "author": "蘋果新聞網",
      "title": "軍演3天沒完沒了！共軍今宣布「繼續對台灣實戰演訓」 檢驗聯合火力｜蘋果新聞網｜蘋果日報 - 蘋果新聞網",
      "description": "中國解放軍從4日開始大動作舉行 3 天的實彈軍演，而東部戰區按計劃預計是今天（7日）中午12點會結束演習，但是稍早微博「東部戰區」發出快訊表示，「8月7日，中國人民解放軍東部戰區按計劃，繼續位台灣周邊海空域進行實戰化聯合演訓，重點檢驗聯合火力對地打擊和遠距離空中打擊能力」。",
      "url": "https://www.appledaily.com.tw/politics/20220807/253DB510691B1C30237B826459",
      "urlToImage": "https://static.appledaily.com.tw/prod/2022-08/253DB510691B1C30237B826459/5a421a64ce4f93043abbd8137b5828ad_large.jpg",
      "publishedAt": "2022-08-07T10:02:19Z",
      "content": null
    },
    {
      "source": { "id": null, "name": "Ettoday.net" },
      "author": "ETtoday新聞雲",
      "title": "南華早報：北京對美日宣洩怒氣後 外交面臨兩難 - ETtoday新聞雲",
      "description": "美國眾議院議長裴洛西（Nancy Pelosi）訪台後，中方透過軍事演習展示武力，也對美日兩國宣洩怒氣。分析指出，這對北京政府來說，似乎是加大外交賭注，如今處於兩難困境之中，到底該讓事態進一步升級，或是努力與其他鄰國站在同一陣線，以避免各國疏離。(第四次台海危機,南華早報,軍演)",
      "url": "https://www.ettoday.net/news/20220807/2311244.htm",
      "urlToImage": "https://cdn2.ettoday.net/images/6497/d6497245.jpg",
      "publishedAt": "2022-08-07T09:46:00Z",
      "content": "8\r\nNancy Pelosi\r\n7\r\nSourabh Gupta\r\n4\r\nLa Trobe UniversityNick Bisley\r\nAntony Blinken\r\nLu Xiang\r\nLi Mingjiang"
    },
    {
      "source": { "id": null, "name": "Ltn.com.tw" },
      "author": "自由時報",
      "title": "共軍實彈射擊結束 外籍航空航班已陸續恢復 - 自由時報",
      "description": "中共解放軍4日起在台灣周邊海域舉行實彈演習至今天中午。而中國發布1到6個臨時危險區飛航公告今天中午12時失效，第7區明天上午10時失效。原本這兩天取消外籍航空航班陸續恢復正常。美國眾議院議長裴洛西8月2日晚間至3日傍晚訪台，中國宣布共軍4日中午12時至7日中午12時，在台灣附近6個海域「進行重要軍事演訓行動，並組織實彈射擊」。航港局4日上午再發布新的航船布告，其中提到中共解放軍的軍演區域多了1處，在東部海域。",
      "url": "https://news.ltn.com.tw/news/politics/breakingnews/4017634",
      "urlToImage": "https://img.ltn.com.tw/Upload/news/600/2022/08/07/php4Ha236.jpg",
      "publishedAt": "2022-08-07T10:06:53Z",
      "content": null
    },
    {
      "source": { "id": null, "name": "Appledaily.com.tw" },
      "author": "蘋果新聞網",
      "title": "軍演3天沒完沒了！共軍今宣布「繼續對台灣實戰演訓」 檢驗聯合火力｜蘋果新聞網｜蘋果日報 - 蘋果新聞網",
      "description": "中國解放軍從4日開始大動作舉行 3 天的實彈軍演，而東部戰區按計劃預計是今天（7日）中午12點會結束演習，但是稍早微博「東部戰區」發出快訊表示，「8月7日，中國人民解放軍東部戰區按計劃，繼續位台灣周邊海空域進行實戰化聯合演訓，重點檢驗聯合火力對地打擊和遠距離空中打擊能力」。",
      "url": "https://www.appledaily.com.tw/politics/20220807/253DB510691B1C30237B826459",
      "urlToImage": "https://static.appledaily.com.tw/prod/2022-08/253DB510691B1C30237B826459/5a421a64ce4f93043abbd8137b5828ad_large.jpg",
      "publishedAt": "2022-08-07T10:02:19Z",
      "content": null
    },
    {
      "source": { "id": null, "name": "Ettoday.net" },
      "author": "ETtoday新聞雲",
      "title": "南華早報：北京對美日宣洩怒氣後 外交面臨兩難 - ETtoday新聞雲",
      "description": "美國眾議院議長裴洛西（Nancy Pelosi）訪台後，中方透過軍事演習展示武力，也對美日兩國宣洩怒氣。分析指出，這對北京政府來說，似乎是加大外交賭注，如今處於兩難困境之中，到底該讓事態進一步升級，或是努力與其他鄰國站在同一陣線，以避免各國疏離。(第四次台海危機,南華早報,軍演)",
      "url": "https://www.ettoday.net/news/20220807/2311244.htm",
      "urlToImage": "https://cdn2.ettoday.net/images/6497/d6497245.jpg",
      "publishedAt": "2022-08-07T09:46:00Z",
      "content": "8\r\nNancy Pelosi\r\n7\r\nSourabh Gupta\r\n4\r\nLa Trobe UniversityNick Bisley\r\nAntony Blinken\r\nLu Xiang\r\nLi Mingjiang"
    },
    {
      "source": { "id": null, "name": "Ltn.com.tw" },
      "author": "自由時報",
      "title": "共軍實彈射擊結束 外籍航空航班已陸續恢復 - 自由時報",
      "description": "中共解放軍4日起在台灣周邊海域舉行實彈演習至今天中午。而中國發布1到6個臨時危險區飛航公告今天中午12時失效，第7區明天上午10時失效。原本這兩天取消外籍航空航班陸續恢復正常。美國眾議院議長裴洛西8月2日晚間至3日傍晚訪台，中國宣布共軍4日中午12時至7日中午12時，在台灣附近6個海域「進行重要軍事演訓行動，並組織實彈射擊」。航港局4日上午再發布新的航船布告，其中提到中共解放軍的軍演區域多了1處，在東部海域。",
      "url": "https://news.ltn.com.tw/news/politics/breakingnews/4017634",
      "urlToImage": "https://img.ltn.com.tw/Upload/news/600/2022/08/07/php4Ha236.jpg",
      "publishedAt": "2022-08-07T10:06:53Z",
      "content": null
    },
    {
      "source": { "id": null, "name": "Appledaily.com.tw" },
      "author": "蘋果新聞網",
      "title": "軍演3天沒完沒了！共軍今宣布「繼續對台灣實戰演訓」 檢驗聯合火力｜蘋果新聞網｜蘋果日報 - 蘋果新聞網",
      "description": "中國解放軍從4日開始大動作舉行 3 天的實彈軍演，而東部戰區按計劃預計是今天（7日）中午12點會結束演習，但是稍早微博「東部戰區」發出快訊表示，「8月7日，中國人民解放軍東部戰區按計劃，繼續位台灣周邊海空域進行實戰化聯合演訓，重點檢驗聯合火力對地打擊和遠距離空中打擊能力」。",
      "url": "https://www.appledaily.com.tw/politics/20220807/253DB510691B1C30237B826459",
      "urlToImage": "https://static.appledaily.com.tw/prod/2022-08/253DB510691B1C30237B826459/5a421a64ce4f93043abbd8137b5828ad_large.jpg",
      "publishedAt": "2022-08-07T10:02:19Z",
      "content": null
    },
    {
      "source": { "id": null, "name": "Ettoday.net" },
      "author": "ETtoday新聞雲",
      "title": "南華早報：北京對美日宣洩怒氣後 外交面臨兩難 - ETtoday新聞雲",
      "description": "美國眾議院議長裴洛西（Nancy Pelosi）訪台後，中方透過軍事演習展示武力，也對美日兩國宣洩怒氣。分析指出，這對北京政府來說，似乎是加大外交賭注，如今處於兩難困境之中，到底該讓事態進一步升級，或是努力與其他鄰國站在同一陣線，以避免各國疏離。(第四次台海危機,南華早報,軍演)",
      "url": "https://www.ettoday.net/news/20220807/2311244.htm",
      "urlToImage": "https://cdn2.ettoday.net/images/6497/d6497245.jpg",
      "publishedAt": "2022-08-07T09:46:00Z",
      "content": "8\r\nNancy Pelosi\r\n7\r\nSourabh Gupta\r\n4\r\nLa Trobe UniversityNick Bisley\r\nAntony Blinken\r\nLu Xiang\r\nLi Mingjiang"
    },
    {
      "source": { "id": null, "name": "Ltn.com.tw" },
      "author": "自由時報",
      "title": "共軍實彈射擊結束 外籍航空航班已陸續恢復 - 自由時報",
      "description": "中共解放軍4日起在台灣周邊海域舉行實彈演習至今天中午。而中國發布1到6個臨時危險區飛航公告今天中午12時失效，第7區明天上午10時失效。原本這兩天取消外籍航空航班陸續恢復正常。美國眾議院議長裴洛西8月2日晚間至3日傍晚訪台，中國宣布共軍4日中午12時至7日中午12時，在台灣附近6個海域「進行重要軍事演訓行動，並組織實彈射擊」。航港局4日上午再發布新的航船布告，其中提到中共解放軍的軍演區域多了1處，在東部海域。",
      "url": "https://news.ltn.com.tw/news/politics/breakingnews/4017634",
      "urlToImage": "https://img.ltn.com.tw/Upload/news/600/2022/08/07/php4Ha236.jpg",
      "publishedAt": "2022-08-07T10:06:53Z",
      "content": null
    },
    {
      "source": { "id": null, "name": "Appledaily.com.tw" },
      "author": "蘋果新聞網",
      "title": "軍演3天沒完沒了！共軍今宣布「繼續對台灣實戰演訓」 檢驗聯合火力｜蘋果新聞網｜蘋果日報 - 蘋果新聞網",
      "description": "中國解放軍從4日開始大動作舉行 3 天的實彈軍演，而東部戰區按計劃預計是今天（7日）中午12點會結束演習，但是稍早微博「東部戰區」發出快訊表示，「8月7日，中國人民解放軍東部戰區按計劃，繼續位台灣周邊海空域進行實戰化聯合演訓，重點檢驗聯合火力對地打擊和遠距離空中打擊能力」。",
      "url": "https://www.appledaily.com.tw/politics/20220807/253DB510691B1C30237B826459",
      "urlToImage": "https://static.appledaily.com.tw/prod/2022-08/253DB510691B1C30237B826459/5a421a64ce4f93043abbd8137b5828ad_large.jpg",
      "publishedAt": "2022-08-07T10:02:19Z",
      "content": null
    },
    {
      "source": { "id": null, "name": "Ettoday.net" },
      "author": "ETtoday新聞雲",
      "title": "南華早報：北京對美日宣洩怒氣後 外交面臨兩難 - ETtoday新聞雲",
      "description": "美國眾議院議長裴洛西（Nancy Pelosi）訪台後，中方透過軍事演習展示武力，也對美日兩國宣洩怒氣。分析指出，這對北京政府來說，似乎是加大外交賭注，如今處於兩難困境之中，到底該讓事態進一步升級，或是努力與其他鄰國站在同一陣線，以避免各國疏離。(第四次台海危機,南華早報,軍演)",
      "url": "https://www.ettoday.net/news/20220807/2311244.htm",
      "urlToImage": "https://cdn2.ettoday.net/images/6497/d6497245.jpg",
      "publishedAt": "2022-08-07T09:46:00Z",
      "content": "8\r\nNancy Pelosi\r\n7\r\nSourabh Gupta\r\n4\r\nLa Trobe UniversityNick Bisley\r\nAntony Blinken\r\nLu Xiang\r\nLi Mingjiang"
    },
    {
      "source": { "id": null, "name": "Ltn.com.tw" },
      "author": "自由時報",
      "title": "共軍實彈射擊結束 外籍航空航班已陸續恢復 - 自由時報",
      "description": "中共解放軍4日起在台灣周邊海域舉行實彈演習至今天中午。而中國發布1到6個臨時危險區飛航公告今天中午12時失效，第7區明天上午10時失效。原本這兩天取消外籍航空航班陸續恢復正常。美國眾議院議長裴洛西8月2日晚間至3日傍晚訪台，中國宣布共軍4日中午12時至7日中午12時，在台灣附近6個海域「進行重要軍事演訓行動，並組織實彈射擊」。航港局4日上午再發布新的航船布告，其中提到中共解放軍的軍演區域多了1處，在東部海域。",
      "url": "https://news.ltn.com.tw/news/politics/breakingnews/4017634",
      "urlToImage": "https://img.ltn.com.tw/Upload/news/600/2022/08/07/php4Ha236.jpg",
      "publishedAt": "2022-08-07T10:06:53Z",
      "content": null
    },
    {
      "source": { "id": null, "name": "Appledaily.com.tw" },
      "author": "蘋果新聞網",
      "title": "軍演3天沒完沒了！共軍今宣布「繼續對台灣實戰演訓」 檢驗聯合火力｜蘋果新聞網｜蘋果日報 - 蘋果新聞網",
      "description": "中國解放軍從4日開始大動作舉行 3 天的實彈軍演，而東部戰區按計劃預計是今天（7日）中午12點會結束演習，但是稍早微博「東部戰區」發出快訊表示，「8月7日，中國人民解放軍東部戰區按計劃，繼續位台灣周邊海空域進行實戰化聯合演訓，重點檢驗聯合火力對地打擊和遠距離空中打擊能力」。",
      "url": "https://www.appledaily.com.tw/politics/20220807/253DB510691B1C30237B826459",
      "urlToImage": "https://static.appledaily.com.tw/prod/2022-08/253DB510691B1C30237B826459/5a421a64ce4f93043abbd8137b5828ad_large.jpg",
      "publishedAt": "2022-08-07T10:02:19Z",
      "content": null
    },
    {
      "source": { "id": null, "name": "Ettoday.net" },
      "author": "ETtoday新聞雲",
      "title": "南華早報：北京對美日宣洩怒氣後 外交面臨兩難 - ETtoday新聞雲",
      "description": "美國眾議院議長裴洛西（Nancy Pelosi）訪台後，中方透過軍事演習展示武力，也對美日兩國宣洩怒氣。分析指出，這對北京政府來說，似乎是加大外交賭注，如今處於兩難困境之中，到底該讓事態進一步升級，或是努力與其他鄰國站在同一陣線，以避免各國疏離。(第四次台海危機,南華早報,軍演)",
      "url": "https://www.ettoday.net/news/20220807/2311244.htm",
      "urlToImage": "https://cdn2.ettoday.net/images/6497/d6497245.jpg",
      "publishedAt": "2022-08-07T09:46:00Z",
      "content": "8\r\nNancy Pelosi\r\n7\r\nSourabh Gupta\r\n4\r\nLa Trobe UniversityNick Bisley\r\nAntony Blinken\r\nLu Xiang\r\nLi Mingjiang"
    },
    {
      "source": { "id": null, "name": "Ltn.com.tw" },
      "author": "自由時報",
      "title": "共軍實彈射擊結束 外籍航空航班已陸續恢復 - 自由時報",
      "description": "中共解放軍4日起在台灣周邊海域舉行實彈演習至今天中午。而中國發布1到6個臨時危險區飛航公告今天中午12時失效，第7區明天上午10時失效。原本這兩天取消外籍航空航班陸續恢復正常。美國眾議院議長裴洛西8月2日晚間至3日傍晚訪台，中國宣布共軍4日中午12時至7日中午12時，在台灣附近6個海域「進行重要軍事演訓行動，並組織實彈射擊」。航港局4日上午再發布新的航船布告，其中提到中共解放軍的軍演區域多了1處，在東部海域。",
      "url": "https://news.ltn.com.tw/news/politics/breakingnews/4017634",
      "urlToImage": "https://img.ltn.com.tw/Upload/news/600/2022/08/07/php4Ha236.jpg",
      "publishedAt": "2022-08-07T10:06:53Z",
      "content": null
    },
    {
      "source": { "id": null, "name": "Appledaily.com.tw" },
      "author": "蘋果新聞網",
      "title": "軍演3天沒完沒了！共軍今宣布「繼續對台灣實戰演訓」 檢驗聯合火力｜蘋果新聞網｜蘋果日報 - 蘋果新聞網",
      "description": "中國解放軍從4日開始大動作舉行 3 天的實彈軍演，而東部戰區按計劃預計是今天（7日）中午12點會結束演習，但是稍早微博「東部戰區」發出快訊表示，「8月7日，中國人民解放軍東部戰區按計劃，繼續位台灣周邊海空域進行實戰化聯合演訓，重點檢驗聯合火力對地打擊和遠距離空中打擊能力」。",
      "url": "https://www.appledaily.com.tw/politics/20220807/253DB510691B1C30237B826459",
      "urlToImage": "https://static.appledaily.com.tw/prod/2022-08/253DB510691B1C30237B826459/5a421a64ce4f93043abbd8137b5828ad_large.jpg",
      "publishedAt": "2022-08-07T10:02:19Z",
      "content": null
    },
    {
      "source": { "id": null, "name": "Ettoday.net" },
      "author": "ETtoday新聞雲",
      "title": "南華早報：北京對美日宣洩怒氣後 外交面臨兩難 - ETtoday新聞雲",
      "description": "美國眾議院議長裴洛西（Nancy Pelosi）訪台後，中方透過軍事演習展示武力，也對美日兩國宣洩怒氣。分析指出，這對北京政府來說，似乎是加大外交賭注，如今處於兩難困境之中，到底該讓事態進一步升級，或是努力與其他鄰國站在同一陣線，以避免各國疏離。(第四次台海危機,南華早報,軍演)",
      "url": "https://www.ettoday.net/news/20220807/2311244.htm",
      "urlToImage": "https://cdn2.ettoday.net/images/6497/d6497245.jpg",
      "publishedAt": "2022-08-07T09:46:00Z",
      "content": "8\r\nNancy Pelosi\r\n7\r\nSourabh Gupta\r\n4\r\nLa Trobe UniversityNick Bisley\r\nAntony Blinken\r\nLu Xiang\r\nLi Mingjiang"
    },
    {
      "source": { "id": null, "name": "Ltn.com.tw" },
      "author": "自由時報",
      "title": "共軍實彈射擊結束 外籍航空航班已陸續恢復 - 自由時報",
      "description": "中共解放軍4日起在台灣周邊海域舉行實彈演習至今天中午。而中國發布1到6個臨時危險區飛航公告今天中午12時失效，第7區明天上午10時失效。原本這兩天取消外籍航空航班陸續恢復正常。美國眾議院議長裴洛西8月2日晚間至3日傍晚訪台，中國宣布共軍4日中午12時至7日中午12時，在台灣附近6個海域「進行重要軍事演訓行動，並組織實彈射擊」。航港局4日上午再發布新的航船布告，其中提到中共解放軍的軍演區域多了1處，在東部海域。",
      "url": "https://news.ltn.com.tw/news/politics/breakingnews/4017634",
      "urlToImage": "https://img.ltn.com.tw/Upload/news/600/2022/08/07/php4Ha236.jpg",
      "publishedAt": "2022-08-07T10:06:53Z",
      "content": null
    },
    {
      "source": { "id": null, "name": "Appledaily.com.tw" },
      "author": "蘋果新聞網",
      "title": "軍演3天沒完沒了！共軍今宣布「繼續對台灣實戰演訓」 檢驗聯合火力｜蘋果新聞網｜蘋果日報 - 蘋果新聞網",
      "description": "中國解放軍從4日開始大動作舉行 3 天的實彈軍演，而東部戰區按計劃預計是今天（7日）中午12點會結束演習，但是稍早微博「東部戰區」發出快訊表示，「8月7日，中國人民解放軍東部戰區按計劃，繼續位台灣周邊海空域進行實戰化聯合演訓，重點檢驗聯合火力對地打擊和遠距離空中打擊能力」。",
      "url": "https://www.appledaily.com.tw/politics/20220807/253DB510691B1C30237B826459",
      "urlToImage": "https://static.appledaily.com.tw/prod/2022-08/253DB510691B1C30237B826459/5a421a64ce4f93043abbd8137b5828ad_large.jpg",
      "publishedAt": "2022-08-07T10:02:19Z",
      "content": null
    },
    {
      "source": { "id": null, "name": "Ettoday.net" },
      "author": "ETtoday新聞雲",
      "title": "南華早報：北京對美日宣洩怒氣後 外交面臨兩難 - ETtoday新聞雲",
      "description": "美國眾議院議長裴洛西（Nancy Pelosi）訪台後，中方透過軍事演習展示武力，也對美日兩國宣洩怒氣。分析指出，這對北京政府來說，似乎是加大外交賭注，如今處於兩難困境之中，到底該讓事態進一步升級，或是努力與其他鄰國站在同一陣線，以避免各國疏離。(第四次台海危機,南華早報,軍演)",
      "url": "https://www.ettoday.net/news/20220807/2311244.htm",
      "urlToImage": "https://cdn2.ettoday.net/images/6497/d6497245.jpg",
      "publishedAt": "2022-08-07T09:46:00Z",
      "content": "8\r\nNancy Pelosi\r\n7\r\nSourabh Gupta\r\n4\r\nLa Trobe UniversityNick Bisley\r\nAntony Blinken\r\nLu Xiang\r\nLi Mingjiang"
    },
    {
      "source": { "id": null, "name": "Ltn.com.tw" },
      "author": "自由時報",
      "title": "共軍實彈射擊結束 外籍航空航班已陸續恢復 - 自由時報",
      "description": "中共解放軍4日起在台灣周邊海域舉行實彈演習至今天中午。而中國發布1到6個臨時危險區飛航公告今天中午12時失效，第7區明天上午10時失效。原本這兩天取消外籍航空航班陸續恢復正常。美國眾議院議長裴洛西8月2日晚間至3日傍晚訪台，中國宣布共軍4日中午12時至7日中午12時，在台灣附近6個海域「進行重要軍事演訓行動，並組織實彈射擊」。航港局4日上午再發布新的航船布告，其中提到中共解放軍的軍演區域多了1處，在東部海域。",
      "url": "https://news.ltn.com.tw/news/politics/breakingnews/4017634",
      "urlToImage": "https://img.ltn.com.tw/Upload/news/600/2022/08/07/php4Ha236.jpg",
      "publishedAt": "2022-08-07T10:06:53Z",
      "content": null
    },
    {
      "source": { "id": null, "name": "Appledaily.com.tw" },
      "author": "蘋果新聞網",
      "title": "軍演3天沒完沒了！共軍今宣布「繼續對台灣實戰演訓」 檢驗聯合火力｜蘋果新聞網｜蘋果日報 - 蘋果新聞網",
      "description": "中國解放軍從4日開始大動作舉行 3 天的實彈軍演，而東部戰區按計劃預計是今天（7日）中午12點會結束演習，但是稍早微博「東部戰區」發出快訊表示，「8月7日，中國人民解放軍東部戰區按計劃，繼續位台灣周邊海空域進行實戰化聯合演訓，重點檢驗聯合火力對地打擊和遠距離空中打擊能力」。",
      "url": "https://www.appledaily.com.tw/politics/20220807/253DB510691B1C30237B826459",
      "urlToImage": "https://static.appledaily.com.tw/prod/2022-08/253DB510691B1C30237B826459/5a421a64ce4f93043abbd8137b5828ad_large.jpg",
      "publishedAt": "2022-08-07T10:02:19Z",
      "content": null
    },
    {
      "source": { "id": null, "name": "Ettoday.net" },
      "author": "ETtoday新聞雲",
      "title": "南華早報：北京對美日宣洩怒氣後 外交面臨兩難 - ETtoday新聞雲",
      "description": "美國眾議院議長裴洛西（Nancy Pelosi）訪台後，中方透過軍事演習展示武力，也對美日兩國宣洩怒氣。分析指出，這對北京政府來說，似乎是加大外交賭注，如今處於兩難困境之中，到底該讓事態進一步升級，或是努力與其他鄰國站在同一陣線，以避免各國疏離。(第四次台海危機,南華早報,軍演)",
      "url": "https://www.ettoday.net/news/20220807/2311244.htm",
      "urlToImage": "https://cdn2.ettoday.net/images/6497/d6497245.jpg",
      "publishedAt": "2022-08-07T09:46:00Z",
      "content": "8\r\nNancy Pelosi\r\n7\r\nSourabh Gupta\r\n4\r\nLa Trobe UniversityNick Bisley\r\nAntony Blinken\r\nLu Xiang\r\nLi Mingjiang"
    },
    {
      "source": { "id": null, "name": "Ltn.com.tw" },
      "author": "自由時報",
      "title": "共軍實彈射擊結束 外籍航空航班已陸續恢復 - 自由時報",
      "description": "中共解放軍4日起在台灣周邊海域舉行實彈演習至今天中午。而中國發布1到6個臨時危險區飛航公告今天中午12時失效，第7區明天上午10時失效。原本這兩天取消外籍航空航班陸續恢復正常。美國眾議院議長裴洛西8月2日晚間至3日傍晚訪台，中國宣布共軍4日中午12時至7日中午12時，在台灣附近6個海域「進行重要軍事演訓行動，並組織實彈射擊」。航港局4日上午再發布新的航船布告，其中提到中共解放軍的軍演區域多了1處，在東部海域。",
      "url": "https://news.ltn.com.tw/news/politics/breakingnews/4017634",
      "urlToImage": "https://img.ltn.com.tw/Upload/news/600/2022/08/07/php4Ha236.jpg",
      "publishedAt": "2022-08-07T10:06:53Z",
      "content": null
    },
    {
      "source": { "id": null, "name": "Appledaily.com.tw" },
      "author": "蘋果新聞網",
      "title": "軍演3天沒完沒了！共軍今宣布「繼續對台灣實戰演訓」 檢驗聯合火力｜蘋果新聞網｜蘋果日報 - 蘋果新聞網",
      "description": "中國解放軍從4日開始大動作舉行 3 天的實彈軍演，而東部戰區按計劃預計是今天（7日）中午12點會結束演習，但是稍早微博「東部戰區」發出快訊表示，「8月7日，中國人民解放軍東部戰區按計劃，繼續位台灣周邊海空域進行實戰化聯合演訓，重點檢驗聯合火力對地打擊和遠距離空中打擊能力」。",
      "url": "https://www.appledaily.com.tw/politics/20220807/253DB510691B1C30237B826459",
      "urlToImage": "https://static.appledaily.com.tw/prod/2022-08/253DB510691B1C30237B826459/5a421a64ce4f93043abbd8137b5828ad_large.jpg",
      "publishedAt": "2022-08-07T10:02:19Z",
      "content": null
    },
    {
      "source": { "id": null, "name": "Ettoday.net" },
      "author": "ETtoday新聞雲",
      "title": "南華早報：北京對美日宣洩怒氣後 外交面臨兩難 - ETtoday新聞雲",
      "description": "美國眾議院議長裴洛西（Nancy Pelosi）訪台後，中方透過軍事演習展示武力，也對美日兩國宣洩怒氣。分析指出，這對北京政府來說，似乎是加大外交賭注，如今處於兩難困境之中，到底該讓事態進一步升級，或是努力與其他鄰國站在同一陣線，以避免各國疏離。(第四次台海危機,南華早報,軍演)",
      "url": "https://www.ettoday.net/news/20220807/2311244.htm",
      "urlToImage": "https://cdn2.ettoday.net/images/6497/d6497245.jpg",
      "publishedAt": "2022-08-07T09:46:00Z",
      "content": "8\r\nNancy Pelosi\r\n7\r\nSourabh Gupta\r\n4\r\nLa Trobe UniversityNick Bisley\r\nAntony Blinken\r\nLu Xiang\r\nLi Mingjiang"
    },
    {
      "source": { "id": null, "name": "Ltn.com.tw" },
      "author": "自由時報",
      "title": "共軍實彈射擊結束 外籍航空航班已陸續恢復 - 自由時報",
      "description": "中共解放軍4日起在台灣周邊海域舉行實彈演習至今天中午。而中國發布1到6個臨時危險區飛航公告今天中午12時失效，第7區明天上午10時失效。原本這兩天取消外籍航空航班陸續恢復正常。美國眾議院議長裴洛西8月2日晚間至3日傍晚訪台，中國宣布共軍4日中午12時至7日中午12時，在台灣附近6個海域「進行重要軍事演訓行動，並組織實彈射擊」。航港局4日上午再發布新的航船布告，其中提到中共解放軍的軍演區域多了1處，在東部海域。",
      "url": "https://news.ltn.com.tw/news/politics/breakingnews/4017634",
      "urlToImage": "https://img.ltn.com.tw/Upload/news/600/2022/08/07/php4Ha236.jpg",
      "publishedAt": "2022-08-07T10:06:53Z",
      "content": null
    },
    {
      "source": { "id": null, "name": "Appledaily.com.tw" },
      "author": "蘋果新聞網",
      "title": "軍演3天沒完沒了！共軍今宣布「繼續對台灣實戰演訓」 檢驗聯合火力｜蘋果新聞網｜蘋果日報 - 蘋果新聞網",
      "description": "中國解放軍從4日開始大動作舉行 3 天的實彈軍演，而東部戰區按計劃預計是今天（7日）中午12點會結束演習，但是稍早微博「東部戰區」發出快訊表示，「8月7日，中國人民解放軍東部戰區按計劃，繼續位台灣周邊海空域進行實戰化聯合演訓，重點檢驗聯合火力對地打擊和遠距離空中打擊能力」。",
      "url": "https://www.appledaily.com.tw/politics/20220807/253DB510691B1C30237B826459",
      "urlToImage": "https://static.appledaily.com.tw/prod/2022-08/253DB510691B1C30237B826459/5a421a64ce4f93043abbd8137b5828ad_large.jpg",
      "publishedAt": "2022-08-07T10:02:19Z",
      "content": null
    },
    {
      "source": { "id": null, "name": "Ettoday.net" },
      "author": "ETtoday新聞雲",
      "title": "南華早報：北京對美日宣洩怒氣後 外交面臨兩難 - ETtoday新聞雲",
      "description": "美國眾議院議長裴洛西（Nancy Pelosi）訪台後，中方透過軍事演習展示武力，也對美日兩國宣洩怒氣。分析指出，這對北京政府來說，似乎是加大外交賭注，如今處於兩難困境之中，到底該讓事態進一步升級，或是努力與其他鄰國站在同一陣線，以避免各國疏離。(第四次台海危機,南華早報,軍演)",
      "url": "https://www.ettoday.net/news/20220807/2311244.htm",
      "urlToImage": "https://cdn2.ettoday.net/images/6497/d6497245.jpg",
      "publishedAt": "2022-08-07T09:46:00Z",
      "content": "8\r\nNancy Pelosi\r\n7\r\nSourabh Gupta\r\n4\r\nLa Trobe UniversityNick Bisley\r\nAntony Blinken\r\nLu Xiang\r\nLi Mingjiang"
    },
    {
      "source": { "id": null, "name": "Ltn.com.tw" },
      "author": "自由時報",
      "title": "共軍實彈射擊結束 外籍航空航班已陸續恢復 - 自由時報",
      "description": "中共解放軍4日起在台灣周邊海域舉行實彈演習至今天中午。而中國發布1到6個臨時危險區飛航公告今天中午12時失效，第7區明天上午10時失效。原本這兩天取消外籍航空航班陸續恢復正常。美國眾議院議長裴洛西8月2日晚間至3日傍晚訪台，中國宣布共軍4日中午12時至7日中午12時，在台灣附近6個海域「進行重要軍事演訓行動，並組織實彈射擊」。航港局4日上午再發布新的航船布告，其中提到中共解放軍的軍演區域多了1處，在東部海域。",
      "url": "https://news.ltn.com.tw/news/politics/breakingnews/4017634",
      "urlToImage": "https://img.ltn.com.tw/Upload/news/600/2022/08/07/php4Ha236.jpg",
      "publishedAt": "2022-08-07T10:06:53Z",
      "content": null
    },
    {
      "source": { "id": null, "name": "Appledaily.com.tw" },
      "author": "蘋果新聞網",
      "title": "軍演3天沒完沒了！共軍今宣布「繼續對台灣實戰演訓」 檢驗聯合火力｜蘋果新聞網｜蘋果日報 - 蘋果新聞網",
      "description": "中國解放軍從4日開始大動作舉行 3 天的實彈軍演，而東部戰區按計劃預計是今天（7日）中午12點會結束演習，但是稍早微博「東部戰區」發出快訊表示，「8月7日，中國人民解放軍東部戰區按計劃，繼續位台灣周邊海空域進行實戰化聯合演訓，重點檢驗聯合火力對地打擊和遠距離空中打擊能力」。",
      "url": "https://www.appledaily.com.tw/politics/20220807/253DB510691B1C30237B826459",
      "urlToImage": "https://static.appledaily.com.tw/prod/2022-08/253DB510691B1C30237B826459/5a421a64ce4f93043abbd8137b5828ad_large.jpg",
      "publishedAt": "2022-08-07T10:02:19Z",
      "content": null
    },
    {
      "source": { "id": null, "name": "Ettoday.net" },
      "author": "ETtoday新聞雲",
      "title": "南華早報：北京對美日宣洩怒氣後 外交面臨兩難 - ETtoday新聞雲",
      "description": "美國眾議院議長裴洛西（Nancy Pelosi）訪台後，中方透過軍事演習展示武力，也對美日兩國宣洩怒氣。分析指出，這對北京政府來說，似乎是加大外交賭注，如今處於兩難困境之中，到底該讓事態進一步升級，或是努力與其他鄰國站在同一陣線，以避免各國疏離。(第四次台海危機,南華早報,軍演)",
      "url": "https://www.ettoday.net/news/20220807/2311244.htm",
      "urlToImage": "https://cdn2.ettoday.net/images/6497/d6497245.jpg",
      "publishedAt": "2022-08-07T09:46:00Z",
      "content": "8\r\nNancy Pelosi\r\n7\r\nSourabh Gupta\r\n4\r\nLa Trobe UniversityNick Bisley\r\nAntony Blinken\r\nLu Xiang\r\nLi Mingjiang"
    },
    {
      "source": { "id": null, "name": "Ltn.com.tw" },
      "author": "自由時報",
      "title": "共軍實彈射擊結束 外籍航空航班已陸續恢復 - 自由時報",
      "description": "中共解放軍4日起在台灣周邊海域舉行實彈演習至今天中午。而中國發布1到6個臨時危險區飛航公告今天中午12時失效，第7區明天上午10時失效。原本這兩天取消外籍航空航班陸續恢復正常。美國眾議院議長裴洛西8月2日晚間至3日傍晚訪台，中國宣布共軍4日中午12時至7日中午12時，在台灣附近6個海域「進行重要軍事演訓行動，並組織實彈射擊」。航港局4日上午再發布新的航船布告，其中提到中共解放軍的軍演區域多了1處，在東部海域。",
      "url": "https://news.ltn.com.tw/news/politics/breakingnews/4017634",
      "urlToImage": "https://img.ltn.com.tw/Upload/news/600/2022/08/07/php4Ha236.jpg",
      "publishedAt": "2022-08-07T10:06:53Z",
      "content": null
    },
    {
      "source": { "id": null, "name": "Appledaily.com.tw" },
      "author": "蘋果新聞網",
      "title": "軍演3天沒完沒了！共軍今宣布「繼續對台灣實戰演訓」 檢驗聯合火力｜蘋果新聞網｜蘋果日報 - 蘋果新聞網",
      "description": "中國解放軍從4日開始大動作舉行 3 天的實彈軍演，而東部戰區按計劃預計是今天（7日）中午12點會結束演習，但是稍早微博「東部戰區」發出快訊表示，「8月7日，中國人民解放軍東部戰區按計劃，繼續位台灣周邊海空域進行實戰化聯合演訓，重點檢驗聯合火力對地打擊和遠距離空中打擊能力」。",
      "url": "https://www.appledaily.com.tw/politics/20220807/253DB510691B1C30237B826459",
      "urlToImage": "https://static.appledaily.com.tw/prod/2022-08/253DB510691B1C30237B826459/5a421a64ce4f93043abbd8137b5828ad_large.jpg",
      "publishedAt": "2022-08-07T10:02:19Z",
      "content": null
    },
    {
      "source": { "id": null, "name": "Ettoday.net" },
      "author": "ETtoday新聞雲",
      "title": "南華早報：北京對美日宣洩怒氣後 外交面臨兩難 - ETtoday新聞雲",
      "description": "美國眾議院議長裴洛西（Nancy Pelosi）訪台後，中方透過軍事演習展示武力，也對美日兩國宣洩怒氣。分析指出，這對北京政府來說，似乎是加大外交賭注，如今處於兩難困境之中，到底該讓事態進一步升級，或是努力與其他鄰國站在同一陣線，以避免各國疏離。(第四次台海危機,南華早報,軍演)",
      "url": "https://www.ettoday.net/news/20220807/2311244.htm",
      "urlToImage": "https://cdn2.ettoday.net/images/6497/d6497245.jpg",
      "publishedAt": "2022-08-07T09:46:00Z",
      "content": "8\r\nNancy Pelosi\r\n7\r\nSourabh Gupta\r\n4\r\nLa Trobe UniversityNick Bisley\r\nAntony Blinken\r\nLu Xiang\r\nLi Mingjiang"
    },
    {
      "source": { "id": null, "name": "Ltn.com.tw" },
      "author": "自由時報",
      "title": "共軍實彈射擊結束 外籍航空航班已陸續恢復 - 自由時報",
      "description": "中共解放軍4日起在台灣周邊海域舉行實彈演習至今天中午。而中國發布1到6個臨時危險區飛航公告今天中午12時失效，第7區明天上午10時失效。原本這兩天取消外籍航空航班陸續恢復正常。美國眾議院議長裴洛西8月2日晚間至3日傍晚訪台，中國宣布共軍4日中午12時至7日中午12時，在台灣附近6個海域「進行重要軍事演訓行動，並組織實彈射擊」。航港局4日上午再發布新的航船布告，其中提到中共解放軍的軍演區域多了1處，在東部海域。",
      "url": "https://news.ltn.com.tw/news/politics/breakingnews/4017634",
      "urlToImage": "https://img.ltn.com.tw/Upload/news/600/2022/08/07/php4Ha236.jpg",
      "publishedAt": "2022-08-07T10:06:53Z",
      "content": null
    },
    {
      "source": { "id": null, "name": "Appledaily.com.tw" },
      "author": "蘋果新聞網",
      "title": "軍演3天沒完沒了！共軍今宣布「繼續對台灣實戰演訓」 檢驗聯合火力｜蘋果新聞網｜蘋果日報 - 蘋果新聞網",
      "description": "中國解放軍從4日開始大動作舉行 3 天的實彈軍演，而東部戰區按計劃預計是今天（7日）中午12點會結束演習，但是稍早微博「東部戰區」發出快訊表示，「8月7日，中國人民解放軍東部戰區按計劃，繼續位台灣周邊海空域進行實戰化聯合演訓，重點檢驗聯合火力對地打擊和遠距離空中打擊能力」。",
      "url": "https://www.appledaily.com.tw/politics/20220807/253DB510691B1C30237B826459",
      "urlToImage": "https://static.appledaily.com.tw/prod/2022-08/253DB510691B1C30237B826459/5a421a64ce4f93043abbd8137b5828ad_large.jpg",
      "publishedAt": "2022-08-07T10:02:19Z",
      "content": null
    },
    {
      "source": { "id": null, "name": "Ettoday.net" },
      "author": "ETtoday新聞雲",
      "title": "南華早報：北京對美日宣洩怒氣後 外交面臨兩難 - ETtoday新聞雲",
      "description": "美國眾議院議長裴洛西（Nancy Pelosi）訪台後，中方透過軍事演習展示武力，也對美日兩國宣洩怒氣。分析指出，這對北京政府來說，似乎是加大外交賭注，如今處於兩難困境之中，到底該讓事態進一步升級，或是努力與其他鄰國站在同一陣線，以避免各國疏離。(第四次台海危機,南華早報,軍演)",
      "url": "https://www.ettoday.net/news/20220807/2311244.htm",
      "urlToImage": "https://cdn2.ettoday.net/images/6497/d6497245.jpg",
      "publishedAt": "2022-08-07T09:46:00Z",
      "content": "8\r\nNancy Pelosi\r\n7\r\nSourabh Gupta\r\n4\r\nLa Trobe UniversityNick Bisley\r\nAntony Blinken\r\nLu Xiang\r\nLi Mingjiang"
    },
    {
      "source": { "id": null, "name": "Ltn.com.tw" },
      "author": "自由時報",
      "title": "共軍實彈射擊結束 外籍航空航班已陸續恢復 - 自由時報",
      "description": "中共解放軍4日起在台灣周邊海域舉行實彈演習至今天中午。而中國發布1到6個臨時危險區飛航公告今天中午12時失效，第7區明天上午10時失效。原本這兩天取消外籍航空航班陸續恢復正常。美國眾議院議長裴洛西8月2日晚間至3日傍晚訪台，中國宣布共軍4日中午12時至7日中午12時，在台灣附近6個海域「進行重要軍事演訓行動，並組織實彈射擊」。航港局4日上午再發布新的航船布告，其中提到中共解放軍的軍演區域多了1處，在東部海域。",
      "url": "https://news.ltn.com.tw/news/politics/breakingnews/4017634",
      "urlToImage": "https://img.ltn.com.tw/Upload/news/600/2022/08/07/php4Ha236.jpg",
      "publishedAt": "2022-08-07T10:06:53Z",
      "content": null
    },
    {
      "source": { "id": null, "name": "Appledaily.com.tw" },
      "author": "蘋果新聞網",
      "title": "軍演3天沒完沒了！共軍今宣布「繼續對台灣實戰演訓」 檢驗聯合火力｜蘋果新聞網｜蘋果日報 - 蘋果新聞網",
      "description": "中國解放軍從4日開始大動作舉行 3 天的實彈軍演，而東部戰區按計劃預計是今天（7日）中午12點會結束演習，但是稍早微博「東部戰區」發出快訊表示，「8月7日，中國人民解放軍東部戰區按計劃，繼續位台灣周邊海空域進行實戰化聯合演訓，重點檢驗聯合火力對地打擊和遠距離空中打擊能力」。",
      "url": "https://www.appledaily.com.tw/politics/20220807/253DB510691B1C30237B826459",
      "urlToImage": "https://static.appledaily.com.tw/prod/2022-08/253DB510691B1C30237B826459/5a421a64ce4f93043abbd8137b5828ad_large.jpg",
      "publishedAt": "2022-08-07T10:02:19Z",
      "content": null
    },
    {
      "source": { "id": null, "name": "Ettoday.net" },
      "author": "ETtoday新聞雲",
      "title": "南華早報：北京對美日宣洩怒氣後 外交面臨兩難 - ETtoday新聞雲",
      "description": "美國眾議院議長裴洛西（Nancy Pelosi）訪台後，中方透過軍事演習展示武力，也對美日兩國宣洩怒氣。分析指出，這對北京政府來說，似乎是加大外交賭注，如今處於兩難困境之中，到底該讓事態進一步升級，或是努力與其他鄰國站在同一陣線，以避免各國疏離。(第四次台海危機,南華早報,軍演)",
      "url": "https://www.ettoday.net/news/20220807/2311244.htm",
      "urlToImage": "https://cdn2.ettoday.net/images/6497/d6497245.jpg",
      "publishedAt": "2022-08-07T09:46:00Z",
      "content": "8\r\nNancy Pelosi\r\n7\r\nSourabh Gupta\r\n4\r\nLa Trobe UniversityNick Bisley\r\nAntony Blinken\r\nLu Xiang\r\nLi Mingjiang"
    },
    {
      "source": { "id": null, "name": "Ltn.com.tw" },
      "author": "自由時報",
      "title": "共軍實彈射擊結束 外籍航空航班已陸續恢復 - 自由時報",
      "description": "中共解放軍4日起在台灣周邊海域舉行實彈演習至今天中午。而中國發布1到6個臨時危險區飛航公告今天中午12時失效，第7區明天上午10時失效。原本這兩天取消外籍航空航班陸續恢復正常。美國眾議院議長裴洛西8月2日晚間至3日傍晚訪台，中國宣布共軍4日中午12時至7日中午12時，在台灣附近6個海域「進行重要軍事演訓行動，並組織實彈射擊」。航港局4日上午再發布新的航船布告，其中提到中共解放軍的軍演區域多了1處，在東部海域。",
      "url": "https://news.ltn.com.tw/news/politics/breakingnews/4017634",
      "urlToImage": "https://img.ltn.com.tw/Upload/news/600/2022/08/07/php4Ha236.jpg",
      "publishedAt": "2022-08-07T10:06:53Z",
      "content": null
    },
    {
      "source": { "id": null, "name": "Appledaily.com.tw" },
      "author": "蘋果新聞網",
      "title": "軍演3天沒完沒了！共軍今宣布「繼續對台灣實戰演訓」 檢驗聯合火力｜蘋果新聞網｜蘋果日報 - 蘋果新聞網",
      "description": "中國解放軍從4日開始大動作舉行 3 天的實彈軍演，而東部戰區按計劃預計是今天（7日）中午12點會結束演習，但是稍早微博「東部戰區」發出快訊表示，「8月7日，中國人民解放軍東部戰區按計劃，繼續位台灣周邊海空域進行實戰化聯合演訓，重點檢驗聯合火力對地打擊和遠距離空中打擊能力」。",
      "url": "https://www.appledaily.com.tw/politics/20220807/253DB510691B1C30237B826459",
      "urlToImage": "https://static.appledaily.com.tw/prod/2022-08/253DB510691B1C30237B826459/5a421a64ce4f93043abbd8137b5828ad_large.jpg",
      "publishedAt": "2022-08-07T10:02:19Z",
      "content": null
    },
    {
      "source": { "id": null, "name": "Ettoday.net" },
      "author": "ETtoday新聞雲",
      "title": "南華早報：北京對美日宣洩怒氣後 外交面臨兩難 - ETtoday新聞雲",
      "description": "美國眾議院議長裴洛西（Nancy Pelosi）訪台後，中方透過軍事演習展示武力，也對美日兩國宣洩怒氣。分析指出，這對北京政府來說，似乎是加大外交賭注，如今處於兩難困境之中，到底該讓事態進一步升級，或是努力與其他鄰國站在同一陣線，以避免各國疏離。(第四次台海危機,南華早報,軍演)",
      "url": "https://www.ettoday.net/news/20220807/2311244.htm",
      "urlToImage": "https://cdn2.ettoday.net/images/6497/d6497245.jpg",
      "publishedAt": "2022-08-07T09:46:00Z",
      "content": "8\r\nNancy Pelosi\r\n7\r\nSourabh Gupta\r\n4\r\nLa Trobe UniversityNick Bisley\r\nAntony Blinken\r\nLu Xiang\r\nLi Mingjiang"
    },
    {
      "source": { "id": null, "name": "Ltn.com.tw" },
      "author": "自由時報",
      "title": "共軍實彈射擊結束 外籍航空航班已陸續恢復 - 自由時報",
      "description": "中共解放軍4日起在台灣周邊海域舉行實彈演習至今天中午。而中國發布1到6個臨時危險區飛航公告今天中午12時失效，第7區明天上午10時失效。原本這兩天取消外籍航空航班陸續恢復正常。美國眾議院議長裴洛西8月2日晚間至3日傍晚訪台，中國宣布共軍4日中午12時至7日中午12時，在台灣附近6個海域「進行重要軍事演訓行動，並組織實彈射擊」。航港局4日上午再發布新的航船布告，其中提到中共解放軍的軍演區域多了1處，在東部海域。",
      "url": "https://news.ltn.com.tw/news/politics/breakingnews/4017634",
      "urlToImage": "https://img.ltn.com.tw/Upload/news/600/2022/08/07/php4Ha236.jpg",
      "publishedAt": "2022-08-07T10:06:53Z",
      "content": null
    },
    {
      "source": { "id": null, "name": "Appledaily.com.tw" },
      "author": "蘋果新聞網",
      "title": "軍演3天沒完沒了！共軍今宣布「繼續對台灣實戰演訓」 檢驗聯合火力｜蘋果新聞網｜蘋果日報 - 蘋果新聞網",
      "description": "中國解放軍從4日開始大動作舉行 3 天的實彈軍演，而東部戰區按計劃預計是今天（7日）中午12點會結束演習，但是稍早微博「東部戰區」發出快訊表示，「8月7日，中國人民解放軍東部戰區按計劃，繼續位台灣周邊海空域進行實戰化聯合演訓，重點檢驗聯合火力對地打擊和遠距離空中打擊能力」。",
      "url": "https://www.appledaily.com.tw/politics/20220807/253DB510691B1C30237B826459",
      "urlToImage": "https://static.appledaily.com.tw/prod/2022-08/253DB510691B1C30237B826459/5a421a64ce4f93043abbd8137b5828ad_large.jpg",
      "publishedAt": "2022-08-07T10:02:19Z",
      "content": null
    },
    {
      "source": { "id": null, "name": "Ettoday.net" },
      "author": "ETtoday新聞雲",
      "title": "南華早報：北京對美日宣洩怒氣後 外交面臨兩難 - ETtoday新聞雲",
      "description": "美國眾議院議長裴洛西（Nancy Pelosi）訪台後，中方透過軍事演習展示武力，也對美日兩國宣洩怒氣。分析指出，這對北京政府來說，似乎是加大外交賭注，如今處於兩難困境之中，到底該讓事態進一步升級，或是努力與其他鄰國站在同一陣線，以避免各國疏離。(第四次台海危機,南華早報,軍演)",
      "url": "https://www.ettoday.net/news/20220807/2311244.htm",
      "urlToImage": "https://cdn2.ettoday.net/images/6497/d6497245.jpg",
      "publishedAt": "2022-08-07T09:46:00Z",
      "content": "8\r\nNancy Pelosi\r\n7\r\nSourabh Gupta\r\n4\r\nLa Trobe UniversityNick Bisley\r\nAntony Blinken\r\nLu Xiang\r\nLi Mingjiang"
    },
    {
      "source": { "id": null, "name": "Ltn.com.tw" },
      "author": "自由時報",
      "title": "共軍實彈射擊結束 外籍航空航班已陸續恢復 - 自由時報",
      "description": "中共解放軍4日起在台灣周邊海域舉行實彈演習至今天中午。而中國發布1到6個臨時危險區飛航公告今天中午12時失效，第7區明天上午10時失效。原本這兩天取消外籍航空航班陸續恢復正常。美國眾議院議長裴洛西8月2日晚間至3日傍晚訪台，中國宣布共軍4日中午12時至7日中午12時，在台灣附近6個海域「進行重要軍事演訓行動，並組織實彈射擊」。航港局4日上午再發布新的航船布告，其中提到中共解放軍的軍演區域多了1處，在東部海域。",
      "url": "https://news.ltn.com.tw/news/politics/breakingnews/4017634",
      "urlToImage": "https://img.ltn.com.tw/Upload/news/600/2022/08/07/php4Ha236.jpg",
      "publishedAt": "2022-08-07T10:06:53Z",
      "content": null
    },
    {
      "source": { "id": null, "name": "Appledaily.com.tw" },
      "author": "蘋果新聞網",
      "title": "軍演3天沒完沒了！共軍今宣布「繼續對台灣實戰演訓」 檢驗聯合火力｜蘋果新聞網｜蘋果日報 - 蘋果新聞網",
      "description": "中國解放軍從4日開始大動作舉行 3 天的實彈軍演，而東部戰區按計劃預計是今天（7日）中午12點會結束演習，但是稍早微博「東部戰區」發出快訊表示，「8月7日，中國人民解放軍東部戰區按計劃，繼續位台灣周邊海空域進行實戰化聯合演訓，重點檢驗聯合火力對地打擊和遠距離空中打擊能力」。",
      "url": "https://www.appledaily.com.tw/politics/20220807/253DB510691B1C30237B826459",
      "urlToImage": "https://static.appledaily.com.tw/prod/2022-08/253DB510691B1C30237B826459/5a421a64ce4f93043abbd8137b5828ad_large.jpg",
      "publishedAt": "2022-08-07T10:02:19Z",
      "content": null
    },
    {
      "source": { "id": null, "name": "Ettoday.net" },
      "author": "ETtoday新聞雲",
      "title": "南華早報：北京對美日宣洩怒氣後 外交面臨兩難 - ETtoday新聞雲",
      "description": "美國眾議院議長裴洛西（Nancy Pelosi）訪台後，中方透過軍事演習展示武力，也對美日兩國宣洩怒氣。分析指出，這對北京政府來說，似乎是加大外交賭注，如今處於兩難困境之中，到底該讓事態進一步升級，或是努力與其他鄰國站在同一陣線，以避免各國疏離。(第四次台海危機,南華早報,軍演)",
      "url": "https://www.ettoday.net/news/20220807/2311244.htm",
      "urlToImage": "https://cdn2.ettoday.net/images/6497/d6497245.jpg",
      "publishedAt": "2022-08-07T09:46:00Z",
      "content": "8\r\nNancy Pelosi\r\n7\r\nSourabh Gupta\r\n4\r\nLa Trobe UniversityNick Bisley\r\nAntony Blinken\r\nLu Xiang\r\nLi Mingjiang"
    },
    {
      "source": { "id": null, "name": "Ltn.com.tw" },
      "author": "自由時報",
      "title": "共軍實彈射擊結束 外籍航空航班已陸續恢復 - 自由時報",
      "description": "中共解放軍4日起在台灣周邊海域舉行實彈演習至今天中午。而中國發布1到6個臨時危險區飛航公告今天中午12時失效，第7區明天上午10時失效。原本這兩天取消外籍航空航班陸續恢復正常。美國眾議院議長裴洛西8月2日晚間至3日傍晚訪台，中國宣布共軍4日中午12時至7日中午12時，在台灣附近6個海域「進行重要軍事演訓行動，並組織實彈射擊」。航港局4日上午再發布新的航船布告，其中提到中共解放軍的軍演區域多了1處，在東部海域。",
      "url": "https://news.ltn.com.tw/news/politics/breakingnews/4017634",
      "urlToImage": "https://img.ltn.com.tw/Upload/news/600/2022/08/07/php4Ha236.jpg",
      "publishedAt": "2022-08-07T10:06:53Z",
      "content": null
    },
    {
      "source": { "id": null, "name": "Appledaily.com.tw" },
      "author": "蘋果新聞網",
      "title": "軍演3天沒完沒了！共軍今宣布「繼續對台灣實戰演訓」 檢驗聯合火力｜蘋果新聞網｜蘋果日報 - 蘋果新聞網",
      "description": "中國解放軍從4日開始大動作舉行 3 天的實彈軍演，而東部戰區按計劃預計是今天（7日）中午12點會結束演習，但是稍早微博「東部戰區」發出快訊表示，「8月7日，中國人民解放軍東部戰區按計劃，繼續位台灣周邊海空域進行實戰化聯合演訓，重點檢驗聯合火力對地打擊和遠距離空中打擊能力」。",
      "url": "https://www.appledaily.com.tw/politics/20220807/253DB510691B1C30237B826459",
      "urlToImage": "https://static.appledaily.com.tw/prod/2022-08/253DB510691B1C30237B826459/5a421a64ce4f93043abbd8137b5828ad_large.jpg",
      "publishedAt": "2022-08-07T10:02:19Z",
      "content": null
    },
    {
      "source": { "id": null, "name": "Ettoday.net" },
      "author": "ETtoday新聞雲",
      "title": "南華早報：北京對美日宣洩怒氣後 外交面臨兩難 - ETtoday新聞雲",
      "description": "美國眾議院議長裴洛西（Nancy Pelosi）訪台後，中方透過軍事演習展示武力，也對美日兩國宣洩怒氣。分析指出，這對北京政府來說，似乎是加大外交賭注，如今處於兩難困境之中，到底該讓事態進一步升級，或是努力與其他鄰國站在同一陣線，以避免各國疏離。(第四次台海危機,南華早報,軍演)",
      "url": "https://www.ettoday.net/news/20220807/2311244.htm",
      "urlToImage": "https://cdn2.ettoday.net/images/6497/d6497245.jpg",
      "publishedAt": "2022-08-07T09:46:00Z",
      "content": "8\r\nNancy Pelosi\r\n7\r\nSourabh Gupta\r\n4\r\nLa Trobe UniversityNick Bisley\r\nAntony Blinken\r\nLu Xiang\r\nLi Mingjiang"
    },
    {
      "source": { "id": null, "name": "Ltn.com.tw" },
      "author": "自由時報",
      "title": "共軍實彈射擊結束 外籍航空航班已陸續恢復 - 自由時報",
      "description": "中共解放軍4日起在台灣周邊海域舉行實彈演習至今天中午。而中國發布1到6個臨時危險區飛航公告今天中午12時失效，第7區明天上午10時失效。原本這兩天取消外籍航空航班陸續恢復正常。美國眾議院議長裴洛西8月2日晚間至3日傍晚訪台，中國宣布共軍4日中午12時至7日中午12時，在台灣附近6個海域「進行重要軍事演訓行動，並組織實彈射擊」。航港局4日上午再發布新的航船布告，其中提到中共解放軍的軍演區域多了1處，在東部海域。",
      "url": "https://news.ltn.com.tw/news/politics/breakingnews/4017634",
      "urlToImage": "https://img.ltn.com.tw/Upload/news/600/2022/08/07/php4Ha236.jpg",
      "publishedAt": "2022-08-07T10:06:53Z",
      "content": null
    },
    {
      "source": { "id": null, "name": "Appledaily.com.tw" },
      "author": "蘋果新聞網",
      "title": "軍演3天沒完沒了！共軍今宣布「繼續對台灣實戰演訓」 檢驗聯合火力｜蘋果新聞網｜蘋果日報 - 蘋果新聞網",
      "description": "中國解放軍從4日開始大動作舉行 3 天的實彈軍演，而東部戰區按計劃預計是今天（7日）中午12點會結束演習，但是稍早微博「東部戰區」發出快訊表示，「8月7日，中國人民解放軍東部戰區按計劃，繼續位台灣周邊海空域進行實戰化聯合演訓，重點檢驗聯合火力對地打擊和遠距離空中打擊能力」。",
      "url": "https://www.appledaily.com.tw/politics/20220807/253DB510691B1C30237B826459",
      "urlToImage": "https://static.appledaily.com.tw/prod/2022-08/253DB510691B1C30237B826459/5a421a64ce4f93043abbd8137b5828ad_large.jpg",
      "publishedAt": "2022-08-07T10:02:19Z",
      "content": null
    },
    {
      "source": { "id": null, "name": "Ettoday.net" },
      "author": "ETtoday新聞雲",
      "title": "南華早報：北京對美日宣洩怒氣後 外交面臨兩難 - ETtoday新聞雲",
      "description": "美國眾議院議長裴洛西（Nancy Pelosi）訪台後，中方透過軍事演習展示武力，也對美日兩國宣洩怒氣。分析指出，這對北京政府來說，似乎是加大外交賭注，如今處於兩難困境之中，到底該讓事態進一步升級，或是努力與其他鄰國站在同一陣線，以避免各國疏離。(第四次台海危機,南華早報,軍演)",
      "url": "https://www.ettoday.net/news/20220807/2311244.htm",
      "urlToImage": "https://cdn2.ettoday.net/images/6497/d6497245.jpg",
      "publishedAt": "2022-08-07T09:46:00Z",
      "content": "8\r\nNancy Pelosi\r\n7\r\nSourabh Gupta\r\n4\r\nLa Trobe UniversityNick Bisley\r\nAntony Blinken\r\nLu Xiang\r\nLi Mingjiang"
    },
    {
      "source": { "id": null, "name": "Ltn.com.tw" },
      "author": "自由時報",
      "title": "共軍實彈射擊結束 外籍航空航班已陸續恢復 - 自由時報",
      "description": "中共解放軍4日起在台灣周邊海域舉行實彈演習至今天中午。而中國發布1到6個臨時危險區飛航公告今天中午12時失效，第7區明天上午10時失效。原本這兩天取消外籍航空航班陸續恢復正常。美國眾議院議長裴洛西8月2日晚間至3日傍晚訪台，中國宣布共軍4日中午12時至7日中午12時，在台灣附近6個海域「進行重要軍事演訓行動，並組織實彈射擊」。航港局4日上午再發布新的航船布告，其中提到中共解放軍的軍演區域多了1處，在東部海域。",
      "url": "https://news.ltn.com.tw/news/politics/breakingnews/4017634",
      "urlToImage": "https://img.ltn.com.tw/Upload/news/600/2022/08/07/php4Ha236.jpg",
      "publishedAt": "2022-08-07T10:06:53Z",
      "content": null
    },
    {
      "source": { "id": null, "name": "Appledaily.com.tw" },
      "author": "蘋果新聞網",
      "title": "軍演3天沒完沒了！共軍今宣布「繼續對台灣實戰演訓」 檢驗聯合火力｜蘋果新聞網｜蘋果日報 - 蘋果新聞網",
      "description": "中國解放軍從4日開始大動作舉行 3 天的實彈軍演，而東部戰區按計劃預計是今天（7日）中午12點會結束演習，但是稍早微博「東部戰區」發出快訊表示，「8月7日，中國人民解放軍東部戰區按計劃，繼續位台灣周邊海空域進行實戰化聯合演訓，重點檢驗聯合火力對地打擊和遠距離空中打擊能力」。",
      "url": "https://www.appledaily.com.tw/politics/20220807/253DB510691B1C30237B826459",
      "urlToImage": "https://static.appledaily.com.tw/prod/2022-08/253DB510691B1C30237B826459/5a421a64ce4f93043abbd8137b5828ad_large.jpg",
      "publishedAt": "2022-08-07T10:02:19Z",
      "content": null
    },
    {
      "source": { "id": null, "name": "Ettoday.net" },
      "author": "ETtoday新聞雲",
      "title": "南華早報：北京對美日宣洩怒氣後 外交面臨兩難 - ETtoday新聞雲",
      "description": "美國眾議院議長裴洛西（Nancy Pelosi）訪台後，中方透過軍事演習展示武力，也對美日兩國宣洩怒氣。分析指出，這對北京政府來說，似乎是加大外交賭注，如今處於兩難困境之中，到底該讓事態進一步升級，或是努力與其他鄰國站在同一陣線，以避免各國疏離。(第四次台海危機,南華早報,軍演)",
      "url": "https://www.ettoday.net/news/20220807/2311244.htm",
      "urlToImage": "https://cdn2.ettoday.net/images/6497/d6497245.jpg",
      "publishedAt": "2022-08-07T09:46:00Z",
      "content": "8\r\nNancy Pelosi\r\n7\r\nSourabh Gupta\r\n4\r\nLa Trobe UniversityNick Bisley\r\nAntony Blinken\r\nLu Xiang\r\nLi Mingjiang"
    },
    {
      "source": { "id": null, "name": "Ltn.com.tw" },
      "author": "自由時報",
      "title": "共軍實彈射擊結束 外籍航空航班已陸續恢復 - 自由時報",
      "description": "中共解放軍4日起在台灣周邊海域舉行實彈演習至今天中午。而中國發布1到6個臨時危險區飛航公告今天中午12時失效，第7區明天上午10時失效。原本這兩天取消外籍航空航班陸續恢復正常。美國眾議院議長裴洛西8月2日晚間至3日傍晚訪台，中國宣布共軍4日中午12時至7日中午12時，在台灣附近6個海域「進行重要軍事演訓行動，並組織實彈射擊」。航港局4日上午再發布新的航船布告，其中提到中共解放軍的軍演區域多了1處，在東部海域。",
      "url": "https://news.ltn.com.tw/news/politics/breakingnews/4017634",
      "urlToImage": "https://img.ltn.com.tw/Upload/news/600/2022/08/07/php4Ha236.jpg",
      "publishedAt": "2022-08-07T10:06:53Z",
      "content": null
    },
    {
      "source": { "id": null, "name": "Appledaily.com.tw" },
      "author": "蘋果新聞網",
      "title": "軍演3天沒完沒了！共軍今宣布「繼續對台灣實戰演訓」 檢驗聯合火力｜蘋果新聞網｜蘋果日報 - 蘋果新聞網",
      "description": "中國解放軍從4日開始大動作舉行 3 天的實彈軍演，而東部戰區按計劃預計是今天（7日）中午12點會結束演習，但是稍早微博「東部戰區」發出快訊表示，「8月7日，中國人民解放軍東部戰區按計劃，繼續位台灣周邊海空域進行實戰化聯合演訓，重點檢驗聯合火力對地打擊和遠距離空中打擊能力」。",
      "url": "https://www.appledaily.com.tw/politics/20220807/253DB510691B1C30237B826459",
      "urlToImage": "https://static.appledaily.com.tw/prod/2022-08/253DB510691B1C30237B826459/5a421a64ce4f93043abbd8137b5828ad_large.jpg",
      "publishedAt": "2022-08-07T10:02:19Z",
      "content": null
    },
    {
      "source": { "id": null, "name": "Ettoday.net" },
      "author": "ETtoday新聞雲",
      "title": "南華早報：北京對美日宣洩怒氣後 外交面臨兩難 - ETtoday新聞雲",
      "description": "美國眾議院議長裴洛西（Nancy Pelosi）訪台後，中方透過軍事演習展示武力，也對美日兩國宣洩怒氣。分析指出，這對北京政府來說，似乎是加大外交賭注，如今處於兩難困境之中，到底該讓事態進一步升級，或是努力與其他鄰國站在同一陣線，以避免各國疏離。(第四次台海危機,南華早報,軍演)",
      "url": "https://www.ettoday.net/news/20220807/2311244.htm",
      "urlToImage": "https://cdn2.ettoday.net/images/6497/d6497245.jpg",
      "publishedAt": "2022-08-07T09:46:00Z",
      "content": "8\r\nNancy Pelosi\r\n7\r\nSourabh Gupta\r\n4\r\nLa Trobe UniversityNick Bisley\r\nAntony Blinken\r\nLu Xiang\r\nLi Mingjiang"
    },
    {
      "source": { "id": null, "name": "Ltn.com.tw" },
      "author": "自由時報",
      "title": "共軍實彈射擊結束 外籍航空航班已陸續恢復 - 自由時報",
      "description": "中共解放軍4日起在台灣周邊海域舉行實彈演習至今天中午。而中國發布1到6個臨時危險區飛航公告今天中午12時失效，第7區明天上午10時失效。原本這兩天取消外籍航空航班陸續恢復正常。美國眾議院議長裴洛西8月2日晚間至3日傍晚訪台，中國宣布共軍4日中午12時至7日中午12時，在台灣附近6個海域「進行重要軍事演訓行動，並組織實彈射擊」。航港局4日上午再發布新的航船布告，其中提到中共解放軍的軍演區域多了1處，在東部海域。",
      "url": "https://news.ltn.com.tw/news/politics/breakingnews/4017634",
      "urlToImage": "https://img.ltn.com.tw/Upload/news/600/2022/08/07/php4Ha236.jpg",
      "publishedAt": "2022-08-07T10:06:53Z",
      "content": null
    },
    {
      "source": { "id": null, "name": "Appledaily.com.tw" },
      "author": "蘋果新聞網",
      "title": "軍演3天沒完沒了！共軍今宣布「繼續對台灣實戰演訓」 檢驗聯合火力｜蘋果新聞網｜蘋果日報 - 蘋果新聞網",
      "description": "中國解放軍從4日開始大動作舉行 3 天的實彈軍演，而東部戰區按計劃預計是今天（7日）中午12點會結束演習，但是稍早微博「東部戰區」發出快訊表示，「8月7日，中國人民解放軍東部戰區按計劃，繼續位台灣周邊海空域進行實戰化聯合演訓，重點檢驗聯合火力對地打擊和遠距離空中打擊能力」。",
      "url": "https://www.appledaily.com.tw/politics/20220807/253DB510691B1C30237B826459",
      "urlToImage": "https://static.appledaily.com.tw/prod/2022-08/253DB510691B1C30237B826459/5a421a64ce4f93043abbd8137b5828ad_large.jpg",
      "publishedAt": "2022-08-07T10:02:19Z",
      "content": null
    },
    {
      "source": { "id": null, "name": "Ettoday.net" },
      "author": "ETtoday新聞雲",
      "title": "南華早報：北京對美日宣洩怒氣後 外交面臨兩難 - ETtoday新聞雲",
      "description": "美國眾議院議長裴洛西（Nancy Pelosi）訪台後，中方透過軍事演習展示武力，也對美日兩國宣洩怒氣。分析指出，這對北京政府來說，似乎是加大外交賭注，如今處於兩難困境之中，到底該讓事態進一步升級，或是努力與其他鄰國站在同一陣線，以避免各國疏離。(第四次台海危機,南華早報,軍演)",
      "url": "https://www.ettoday.net/news/20220807/2311244.htm",
      "urlToImage": "https://cdn2.ettoday.net/images/6497/d6497245.jpg",
      "publishedAt": "2022-08-07T09:46:00Z",
      "content": "8\r\nNancy Pelosi\r\n7\r\nSourabh Gupta\r\n4\r\nLa Trobe UniversityNick Bisley\r\nAntony Blinken\r\nLu Xiang\r\nLi Mingjiang"
    },
    {
      "source": { "id": null, "name": "Ltn.com.tw" },
      "author": "自由時報",
      "title": "共軍實彈射擊結束 外籍航空航班已陸續恢復 - 自由時報",
      "description": "中共解放軍4日起在台灣周邊海域舉行實彈演習至今天中午。而中國發布1到6個臨時危險區飛航公告今天中午12時失效，第7區明天上午10時失效。原本這兩天取消外籍航空航班陸續恢復正常。美國眾議院議長裴洛西8月2日晚間至3日傍晚訪台，中國宣布共軍4日中午12時至7日中午12時，在台灣附近6個海域「進行重要軍事演訓行動，並組織實彈射擊」。航港局4日上午再發布新的航船布告，其中提到中共解放軍的軍演區域多了1處，在東部海域。",
      "url": "https://news.ltn.com.tw/news/politics/breakingnews/4017634",
      "urlToImage": "https://img.ltn.com.tw/Upload/news/600/2022/08/07/php4Ha236.jpg",
      "publishedAt": "2022-08-07T10:06:53Z",
      "content": null
    },
    {
      "source": { "id": null, "name": "Appledaily.com.tw" },
      "author": "蘋果新聞網",
      "title": "軍演3天沒完沒了！共軍今宣布「繼續對台灣實戰演訓」 檢驗聯合火力｜蘋果新聞網｜蘋果日報 - 蘋果新聞網",
      "description": "中國解放軍從4日開始大動作舉行 3 天的實彈軍演，而東部戰區按計劃預計是今天（7日）中午12點會結束演習，但是稍早微博「東部戰區」發出快訊表示，「8月7日，中國人民解放軍東部戰區按計劃，繼續位台灣周邊海空域進行實戰化聯合演訓，重點檢驗聯合火力對地打擊和遠距離空中打擊能力」。",
      "url": "https://www.appledaily.com.tw/politics/20220807/253DB510691B1C30237B826459",
      "urlToImage": "https://static.appledaily.com.tw/prod/2022-08/253DB510691B1C30237B826459/5a421a64ce4f93043abbd8137b5828ad_large.jpg",
      "publishedAt": "2022-08-07T10:02:19Z",
      "content": null
    },
    {
      "source": { "id": null, "name": "Ettoday.net" },
      "author": "ETtoday新聞雲",
      "title": "南華早報：北京對美日宣洩怒氣後 外交面臨兩難 - ETtoday新聞雲",
      "description": "美國眾議院議長裴洛西（Nancy Pelosi）訪台後，中方透過軍事演習展示武力，也對美日兩國宣洩怒氣。分析指出，這對北京政府來說，似乎是加大外交賭注，如今處於兩難困境之中，到底該讓事態進一步升級，或是努力與其他鄰國站在同一陣線，以避免各國疏離。(第四次台海危機,南華早報,軍演)",
      "url": "https://www.ettoday.net/news/20220807/2311244.htm",
      "urlToImage": "https://cdn2.ettoday.net/images/6497/d6497245.jpg",
      "publishedAt": "2022-08-07T09:46:00Z",
      "content": "8\r\nNancy Pelosi\r\n7\r\nSourabh Gupta\r\n4\r\nLa Trobe UniversityNick Bisley\r\nAntony Blinken\r\nLu Xiang\r\nLi Mingjiang"
    },
    {
      "source": { "id": null, "name": "Ltn.com.tw" },
      "author": "自由時報",
      "title": "共軍實彈射擊結束 外籍航空航班已陸續恢復 - 自由時報",
      "description": "中共解放軍4日起在台灣周邊海域舉行實彈演習至今天中午。而中國發布1到6個臨時危險區飛航公告今天中午12時失效，第7區明天上午10時失效。原本這兩天取消外籍航空航班陸續恢復正常。美國眾議院議長裴洛西8月2日晚間至3日傍晚訪台，中國宣布共軍4日中午12時至7日中午12時，在台灣附近6個海域「進行重要軍事演訓行動，並組織實彈射擊」。航港局4日上午再發布新的航船布告，其中提到中共解放軍的軍演區域多了1處，在東部海域。",
      "url": "https://news.ltn.com.tw/news/politics/breakingnews/4017634",
      "urlToImage": "https://img.ltn.com.tw/Upload/news/600/2022/08/07/php4Ha236.jpg",
      "publishedAt": "2022-08-07T10:06:53Z",
      "content": null
    },
    {
      "source": { "id": null, "name": "Appledaily.com.tw" },
      "author": "蘋果新聞網",
      "title": "軍演3天沒完沒了！共軍今宣布「繼續對台灣實戰演訓」 檢驗聯合火力｜蘋果新聞網｜蘋果日報 - 蘋果新聞網",
      "description": "中國解放軍從4日開始大動作舉行 3 天的實彈軍演，而東部戰區按計劃預計是今天（7日）中午12點會結束演習，但是稍早微博「東部戰區」發出快訊表示，「8月7日，中國人民解放軍東部戰區按計劃，繼續位台灣周邊海空域進行實戰化聯合演訓，重點檢驗聯合火力對地打擊和遠距離空中打擊能力」。",
      "url": "https://www.appledaily.com.tw/politics/20220807/253DB510691B1C30237B826459",
      "urlToImage": "https://static.appledaily.com.tw/prod/2022-08/253DB510691B1C30237B826459/5a421a64ce4f93043abbd8137b5828ad_large.jpg",
      "publishedAt": "2022-08-07T10:02:19Z",
      "content": null
    },
    {
      "source": { "id": null, "name": "Ettoday.net" },
      "author": "ETtoday新聞雲",
      "title": "南華早報：北京對美日宣洩怒氣後 外交面臨兩難 - ETtoday新聞雲",
      "description": "美國眾議院議長裴洛西（Nancy Pelosi）訪台後，中方透過軍事演習展示武力，也對美日兩國宣洩怒氣。分析指出，這對北京政府來說，似乎是加大外交賭注，如今處於兩難困境之中，到底該讓事態進一步升級，或是努力與其他鄰國站在同一陣線，以避免各國疏離。(第四次台海危機,南華早報,軍演)",
      "url": "https://www.ettoday.net/news/20220807/2311244.htm",
      "urlToImage": "https://cdn2.ettoday.net/images/6497/d6497245.jpg",
      "publishedAt": "2022-08-07T09:46:00Z",
      "content": "8\r\nNancy Pelosi\r\n7\r\nSourabh Gupta\r\n4\r\nLa Trobe UniversityNick Bisley\r\nAntony Blinken\r\nLu Xiang\r\nLi Mingjiang"
    },
    {
      "source": { "id": null, "name": "Ltn.com.tw" },
      "author": "自由時報",
      "title": "共軍實彈射擊結束 外籍航空航班已陸續恢復 - 自由時報",
      "description": "中共解放軍4日起在台灣周邊海域舉行實彈演習至今天中午。而中國發布1到6個臨時危險區飛航公告今天中午12時失效，第7區明天上午10時失效。原本這兩天取消外籍航空航班陸續恢復正常。美國眾議院議長裴洛西8月2日晚間至3日傍晚訪台，中國宣布共軍4日中午12時至7日中午12時，在台灣附近6個海域「進行重要軍事演訓行動，並組織實彈射擊」。航港局4日上午再發布新的航船布告，其中提到中共解放軍的軍演區域多了1處，在東部海域。",
      "url": "https://news.ltn.com.tw/news/politics/breakingnews/4017634",
      "urlToImage": "https://img.ltn.com.tw/Upload/news/600/2022/08/07/php4Ha236.jpg",
      "publishedAt": "2022-08-07T10:06:53Z",
      "content": null
    },
    {
      "source": { "id": null, "name": "Appledaily.com.tw" },
      "author": "蘋果新聞網",
      "title": "軍演3天沒完沒了！共軍今宣布「繼續對台灣實戰演訓」 檢驗聯合火力｜蘋果新聞網｜蘋果日報 - 蘋果新聞網",
      "description": "中國解放軍從4日開始大動作舉行 3 天的實彈軍演，而東部戰區按計劃預計是今天（7日）中午12點會結束演習，但是稍早微博「東部戰區」發出快訊表示，「8月7日，中國人民解放軍東部戰區按計劃，繼續位台灣周邊海空域進行實戰化聯合演訓，重點檢驗聯合火力對地打擊和遠距離空中打擊能力」。",
      "url": "https://www.appledaily.com.tw/politics/20220807/253DB510691B1C30237B826459",
      "urlToImage": "https://static.appledaily.com.tw/prod/2022-08/253DB510691B1C30237B826459/5a421a64ce4f93043abbd8137b5828ad_large.jpg",
      "publishedAt": "2022-08-07T10:02:19Z",
      "content": null
    },
    {
      "source": { "id": null, "name": "Ettoday.net" },
      "author": "ETtoday新聞雲",
      "title": "南華早報：北京對美日宣洩怒氣後 外交面臨兩難 - ETtoday新聞雲",
      "description": "美國眾議院議長裴洛西（Nancy Pelosi）訪台後，中方透過軍事演習展示武力，也對美日兩國宣洩怒氣。分析指出，這對北京政府來說，似乎是加大外交賭注，如今處於兩難困境之中，到底該讓事態進一步升級，或是努力與其他鄰國站在同一陣線，以避免各國疏離。(第四次台海危機,南華早報,軍演)",
      "url": "https://www.ettoday.net/news/20220807/2311244.htm",
      "urlToImage": "https://cdn2.ettoday.net/images/6497/d6497245.jpg",
      "publishedAt": "2022-08-07T09:46:00Z",
      "content": "8\r\nNancy Pelosi\r\n7\r\nSourabh Gupta\r\n4\r\nLa Trobe UniversityNick Bisley\r\nAntony Blinken\r\nLu Xiang\r\nLi Mingjiang"
    },
    {
      "source": { "id": null, "name": "Ltn.com.tw" },
      "author": "自由時報",
      "title": "共軍實彈射擊結束 外籍航空航班已陸續恢復 - 自由時報",
      "description": "中共解放軍4日起在台灣周邊海域舉行實彈演習至今天中午。而中國發布1到6個臨時危險區飛航公告今天中午12時失效，第7區明天上午10時失效。原本這兩天取消外籍航空航班陸續恢復正常。美國眾議院議長裴洛西8月2日晚間至3日傍晚訪台，中國宣布共軍4日中午12時至7日中午12時，在台灣附近6個海域「進行重要軍事演訓行動，並組織實彈射擊」。航港局4日上午再發布新的航船布告，其中提到中共解放軍的軍演區域多了1處，在東部海域。",
      "url": "https://news.ltn.com.tw/news/politics/breakingnews/4017634",
      "urlToImage": "https://img.ltn.com.tw/Upload/news/600/2022/08/07/php4Ha236.jpg",
      "publishedAt": "2022-08-07T10:06:53Z",
      "content": null
    },
    {
      "source": { "id": null, "name": "Appledaily.com.tw" },
      "author": "蘋果新聞網",
      "title": "軍演3天沒完沒了！共軍今宣布「繼續對台灣實戰演訓」 檢驗聯合火力｜蘋果新聞網｜蘋果日報 - 蘋果新聞網",
      "description": "中國解放軍從4日開始大動作舉行 3 天的實彈軍演，而東部戰區按計劃預計是今天（7日）中午12點會結束演習，但是稍早微博「東部戰區」發出快訊表示，「8月7日，中國人民解放軍東部戰區按計劃，繼續位台灣周邊海空域進行實戰化聯合演訓，重點檢驗聯合火力對地打擊和遠距離空中打擊能力」。",
      "url": "https://www.appledaily.com.tw/politics/20220807/253DB510691B1C30237B826459",
      "urlToImage": "https://static.appledaily.com.tw/prod/2022-08/253DB510691B1C30237B826459/5a421a64ce4f93043abbd8137b5828ad_large.jpg",
      "publishedAt": "2022-08-07T10:02:19Z",
      "content": null
    },
    {
      "source": { "id": null, "name": "Ettoday.net" },
      "author": "ETtoday新聞雲",
      "title": "南華早報：北京對美日宣洩怒氣後 外交面臨兩難 - ETtoday新聞雲",
      "description": "美國眾議院議長裴洛西（Nancy Pelosi）訪台後，中方透過軍事演習展示武力，也對美日兩國宣洩怒氣。分析指出，這對北京政府來說，似乎是加大外交賭注，如今處於兩難困境之中，到底該讓事態進一步升級，或是努力與其他鄰國站在同一陣線，以避免各國疏離。(第四次台海危機,南華早報,軍演)",
      "url": "https://www.ettoday.net/news/20220807/2311244.htm",
      "urlToImage": "https://cdn2.ettoday.net/images/6497/d6497245.jpg",
      "publishedAt": "2022-08-07T09:46:00Z",
      "content": "8\r\nNancy Pelosi\r\n7\r\nSourabh Gupta\r\n4\r\nLa Trobe UniversityNick Bisley\r\nAntony Blinken\r\nLu Xiang\r\nLi Mingjiang"
    },
    {
      "source": { "id": null, "name": "Ltn.com.tw" },
      "author": "自由時報",
      "title": "共軍實彈射擊結束 外籍航空航班已陸續恢復 - 自由時報",
      "description": "中共解放軍4日起在台灣周邊海域舉行實彈演習至今天中午。而中國發布1到6個臨時危險區飛航公告今天中午12時失效，第7區明天上午10時失效。原本這兩天取消外籍航空航班陸續恢復正常。美國眾議院議長裴洛西8月2日晚間至3日傍晚訪台，中國宣布共軍4日中午12時至7日中午12時，在台灣附近6個海域「進行重要軍事演訓行動，並組織實彈射擊」。航港局4日上午再發布新的航船布告，其中提到中共解放軍的軍演區域多了1處，在東部海域。",
      "url": "https://news.ltn.com.tw/news/politics/breakingnews/4017634",
      "urlToImage": "https://img.ltn.com.tw/Upload/news/600/2022/08/07/php4Ha236.jpg",
      "publishedAt": "2022-08-07T10:06:53Z",
      "content": null
    },
    {
      "source": { "id": null, "name": "Appledaily.com.tw" },
      "author": "蘋果新聞網",
      "title": "軍演3天沒完沒了！共軍今宣布「繼續對台灣實戰演訓」 檢驗聯合火力｜蘋果新聞網｜蘋果日報 - 蘋果新聞網",
      "description": "中國解放軍從4日開始大動作舉行 3 天的實彈軍演，而東部戰區按計劃預計是今天（7日）中午12點會結束演習，但是稍早微博「東部戰區」發出快訊表示，「8月7日，中國人民解放軍東部戰區按計劃，繼續位台灣周邊海空域進行實戰化聯合演訓，重點檢驗聯合火力對地打擊和遠距離空中打擊能力」。",
      "url": "https://www.appledaily.com.tw/politics/20220807/253DB510691B1C30237B826459",
      "urlToImage": "https://static.appledaily.com.tw/prod/2022-08/253DB510691B1C30237B826459/5a421a64ce4f93043abbd8137b5828ad_large.jpg",
      "publishedAt": "2022-08-07T10:02:19Z",
      "content": null
    },
    {
      "source": { "id": null, "name": "Ettoday.net" },
      "author": "ETtoday新聞雲",
      "title": "南華早報：北京對美日宣洩怒氣後 外交面臨兩難 - ETtoday新聞雲",
      "description": "美國眾議院議長裴洛西（Nancy Pelosi）訪台後，中方透過軍事演習展示武力，也對美日兩國宣洩怒氣。分析指出，這對北京政府來說，似乎是加大外交賭注，如今處於兩難困境之中，到底該讓事態進一步升級，或是努力與其他鄰國站在同一陣線，以避免各國疏離。(第四次台海危機,南華早報,軍演)",
      "url": "https://www.ettoday.net/news/20220807/2311244.htm",
      "urlToImage": "https://cdn2.ettoday.net/images/6497/d6497245.jpg",
      "publishedAt": "2022-08-07T09:46:00Z",
      "content": "8\r\nNancy Pelosi\r\n7\r\nSourabh Gupta\r\n4\r\nLa Trobe UniversityNick Bisley\r\nAntony Blinken\r\nLu Xiang\r\nLi Mingjiang"
    },
    {
      "source": { "id": null, "name": "Ltn.com.tw" },
      "author": "自由時報",
      "title": "共軍實彈射擊結束 外籍航空航班已陸續恢復 - 自由時報",
      "description": "中共解放軍4日起在台灣周邊海域舉行實彈演習至今天中午。而中國發布1到6個臨時危險區飛航公告今天中午12時失效，第7區明天上午10時失效。原本這兩天取消外籍航空航班陸續恢復正常。美國眾議院議長裴洛西8月2日晚間至3日傍晚訪台，中國宣布共軍4日中午12時至7日中午12時，在台灣附近6個海域「進行重要軍事演訓行動，並組織實彈射擊」。航港局4日上午再發布新的航船布告，其中提到中共解放軍的軍演區域多了1處，在東部海域。",
      "url": "https://news.ltn.com.tw/news/politics/breakingnews/4017634",
      "urlToImage": "https://img.ltn.com.tw/Upload/news/600/2022/08/07/php4Ha236.jpg",
      "publishedAt": "2022-08-07T10:06:53Z",
      "content": null
    },
    {
      "source": { "id": null, "name": "Appledaily.com.tw" },
      "author": "蘋果新聞網",
      "title": "軍演3天沒完沒了！共軍今宣布「繼續對台灣實戰演訓」 檢驗聯合火力｜蘋果新聞網｜蘋果日報 - 蘋果新聞網",
      "description": "中國解放軍從4日開始大動作舉行 3 天的實彈軍演，而東部戰區按計劃預計是今天（7日）中午12點會結束演習，但是稍早微博「東部戰區」發出快訊表示，「8月7日，中國人民解放軍東部戰區按計劃，繼續位台灣周邊海空域進行實戰化聯合演訓，重點檢驗聯合火力對地打擊和遠距離空中打擊能力」。",
      "url": "https://www.appledaily.com.tw/politics/20220807/253DB510691B1C30237B826459",
      "urlToImage": "https://static.appledaily.com.tw/prod/2022-08/253DB510691B1C30237B826459/5a421a64ce4f93043abbd8137b5828ad_large.jpg",
      "publishedAt": "2022-08-07T10:02:19Z",
      "content": null
    },
    {
      "source": { "id": null, "name": "Ettoday.net" },
      "author": "ETtoday新聞雲",
      "title": "南華早報：北京對美日宣洩怒氣後 外交面臨兩難 - ETtoday新聞雲",
      "description": "美國眾議院議長裴洛西（Nancy Pelosi）訪台後，中方透過軍事演習展示武力，也對美日兩國宣洩怒氣。分析指出，這對北京政府來說，似乎是加大外交賭注，如今處於兩難困境之中，到底該讓事態進一步升級，或是努力與其他鄰國站在同一陣線，以避免各國疏離。(第四次台海危機,南華早報,軍演)",
      "url": "https://www.ettoday.net/news/20220807/2311244.htm",
      "urlToImage": "https://cdn2.ettoday.net/images/6497/d6497245.jpg",
      "publishedAt": "2022-08-07T09:46:00Z",
      "content": "8\r\nNancy Pelosi\r\n7\r\nSourabh Gupta\r\n4\r\nLa Trobe UniversityNick Bisley\r\nAntony Blinken\r\nLu Xiang\r\nLi Mingjiang"
    },
    {
      "source": { "id": null, "name": "Ltn.com.tw" },
      "author": "自由時報",
      "title": "共軍實彈射擊結束 外籍航空航班已陸續恢復 - 自由時報",
      "description": "中共解放軍4日起在台灣周邊海域舉行實彈演習至今天中午。而中國發布1到6個臨時危險區飛航公告今天中午12時失效，第7區明天上午10時失效。原本這兩天取消外籍航空航班陸續恢復正常。美國眾議院議長裴洛西8月2日晚間至3日傍晚訪台，中國宣布共軍4日中午12時至7日中午12時，在台灣附近6個海域「進行重要軍事演訓行動，並組織實彈射擊」。航港局4日上午再發布新的航船布告，其中提到中共解放軍的軍演區域多了1處，在東部海域。",
      "url": "https://news.ltn.com.tw/news/politics/breakingnews/4017634",
      "urlToImage": "https://img.ltn.com.tw/Upload/news/600/2022/08/07/php4Ha236.jpg",
      "publishedAt": "2022-08-07T10:06:53Z",
      "content": null
    },
    {
      "source": { "id": null, "name": "Appledaily.com.tw" },
      "author": "蘋果新聞網",
      "title": "軍演3天沒完沒了！共軍今宣布「繼續對台灣實戰演訓」 檢驗聯合火力｜蘋果新聞網｜蘋果日報 - 蘋果新聞網",
      "description": "中國解放軍從4日開始大動作舉行 3 天的實彈軍演，而東部戰區按計劃預計是今天（7日）中午12點會結束演習，但是稍早微博「東部戰區」發出快訊表示，「8月7日，中國人民解放軍東部戰區按計劃，繼續位台灣周邊海空域進行實戰化聯合演訓，重點檢驗聯合火力對地打擊和遠距離空中打擊能力」。",
      "url": "https://www.appledaily.com.tw/politics/20220807/253DB510691B1C30237B826459",
      "urlToImage": "https://static.appledaily.com.tw/prod/2022-08/253DB510691B1C30237B826459/5a421a64ce4f93043abbd8137b5828ad_large.jpg",
      "publishedAt": "2022-08-07T10:02:19Z",
      "content": null
    },
    {
      "source": { "id": null, "name": "Ettoday.net" },
      "author": "ETtoday新聞雲",
      "title": "南華早報：北京對美日宣洩怒氣後 外交面臨兩難 - ETtoday新聞雲",
      "description": "美國眾議院議長裴洛西（Nancy Pelosi）訪台後，中方透過軍事演習展示武力，也對美日兩國宣洩怒氣。分析指出，這對北京政府來說，似乎是加大外交賭注，如今處於兩難困境之中，到底該讓事態進一步升級，或是努力與其他鄰國站在同一陣線，以避免各國疏離。(第四次台海危機,南華早報,軍演)",
      "url": "https://www.ettoday.net/news/20220807/2311244.htm",
      "urlToImage": "https://cdn2.ettoday.net/images/6497/d6497245.jpg",
      "publishedAt": "2022-08-07T09:46:00Z",
      "content": "8\r\nNancy Pelosi\r\n7\r\nSourabh Gupta\r\n4\r\nLa Trobe UniversityNick Bisley\r\nAntony Blinken\r\nLu Xiang\r\nLi Mingjiang"
    },
    {
      "source": { "id": null, "name": "Ltn.com.tw" },
      "author": "自由時報",
      "title": "共軍實彈射擊結束 外籍航空航班已陸續恢復 - 自由時報",
      "description": "中共解放軍4日起在台灣周邊海域舉行實彈演習至今天中午。而中國發布1到6個臨時危險區飛航公告今天中午12時失效，第7區明天上午10時失效。原本這兩天取消外籍航空航班陸續恢復正常。美國眾議院議長裴洛西8月2日晚間至3日傍晚訪台，中國宣布共軍4日中午12時至7日中午12時，在台灣附近6個海域「進行重要軍事演訓行動，並組織實彈射擊」。航港局4日上午再發布新的航船布告，其中提到中共解放軍的軍演區域多了1處，在東部海域。",
      "url": "https://news.ltn.com.tw/news/politics/breakingnews/4017634",
      "urlToImage": "https://img.ltn.com.tw/Upload/news/600/2022/08/07/php4Ha236.jpg",
      "publishedAt": "2022-08-07T10:06:53Z",
      "content": null
    },
    {
      "source": { "id": null, "name": "Appledaily.com.tw" },
      "author": "蘋果新聞網",
      "title": "軍演3天沒完沒了！共軍今宣布「繼續對台灣實戰演訓」 檢驗聯合火力｜蘋果新聞網｜蘋果日報 - 蘋果新聞網",
      "description": "中國解放軍從4日開始大動作舉行 3 天的實彈軍演，而東部戰區按計劃預計是今天（7日）中午12點會結束演習，但是稍早微博「東部戰區」發出快訊表示，「8月7日，中國人民解放軍東部戰區按計劃，繼續位台灣周邊海空域進行實戰化聯合演訓，重點檢驗聯合火力對地打擊和遠距離空中打擊能力」。",
      "url": "https://www.appledaily.com.tw/politics/20220807/253DB510691B1C30237B826459",
      "urlToImage": "https://static.appledaily.com.tw/prod/2022-08/253DB510691B1C30237B826459/5a421a64ce4f93043abbd8137b5828ad_large.jpg",
      "publishedAt": "2022-08-07T10:02:19Z",
      "content": null
    },
    {
      "source": { "id": null, "name": "Ettoday.net" },
      "author": "ETtoday新聞雲",
      "title": "南華早報：北京對美日宣洩怒氣後 外交面臨兩難 - ETtoday新聞雲",
      "description": "美國眾議院議長裴洛西（Nancy Pelosi）訪台後，中方透過軍事演習展示武力，也對美日兩國宣洩怒氣。分析指出，這對北京政府來說，似乎是加大外交賭注，如今處於兩難困境之中，到底該讓事態進一步升級，或是努力與其他鄰國站在同一陣線，以避免各國疏離。(第四次台海危機,南華早報,軍演)",
      "url": "https://www.ettoday.net/news/20220807/2311244.htm",
      "urlToImage": "https://cdn2.ettoday.net/images/6497/d6497245.jpg",
      "publishedAt": "2022-08-07T09:46:00Z",
      "content": "8\r\nNancy Pelosi\r\n7\r\nSourabh Gupta\r\n4\r\nLa Trobe UniversityNick Bisley\r\nAntony Blinken\r\nLu Xiang\r\nLi Mingjiang"
    },
    {
      "source": { "id": null, "name": "Ltn.com.tw" },
      "author": "自由時報",
      "title": "共軍實彈射擊結束 外籍航空航班已陸續恢復 - 自由時報",
      "description": "中共解放軍4日起在台灣周邊海域舉行實彈演習至今天中午。而中國發布1到6個臨時危險區飛航公告今天中午12時失效，第7區明天上午10時失效。原本這兩天取消外籍航空航班陸續恢復正常。美國眾議院議長裴洛西8月2日晚間至3日傍晚訪台，中國宣布共軍4日中午12時至7日中午12時，在台灣附近6個海域「進行重要軍事演訓行動，並組織實彈射擊」。航港局4日上午再發布新的航船布告，其中提到中共解放軍的軍演區域多了1處，在東部海域。",
      "url": "https://news.ltn.com.tw/news/politics/breakingnews/4017634",
      "urlToImage": "https://img.ltn.com.tw/Upload/news/600/2022/08/07/php4Ha236.jpg",
      "publishedAt": "2022-08-07T10:06:53Z",
      "content": null
    },
    {
      "source": { "id": null, "name": "Appledaily.com.tw" },
      "author": "蘋果新聞網",
      "title": "軍演3天沒完沒了！共軍今宣布「繼續對台灣實戰演訓」 檢驗聯合火力｜蘋果新聞網｜蘋果日報 - 蘋果新聞網",
      "description": "中國解放軍從4日開始大動作舉行 3 天的實彈軍演，而東部戰區按計劃預計是今天（7日）中午12點會結束演習，但是稍早微博「東部戰區」發出快訊表示，「8月7日，中國人民解放軍東部戰區按計劃，繼續位台灣周邊海空域進行實戰化聯合演訓，重點檢驗聯合火力對地打擊和遠距離空中打擊能力」。",
      "url": "https://www.appledaily.com.tw/politics/20220807/253DB510691B1C30237B826459",
      "urlToImage": "https://static.appledaily.com.tw/prod/2022-08/253DB510691B1C30237B826459/5a421a64ce4f93043abbd8137b5828ad_large.jpg",
      "publishedAt": "2022-08-07T10:02:19Z",
      "content": null
    },
    {
      "source": { "id": null, "name": "Ettoday.net" },
      "author": "ETtoday新聞雲",
      "title": "南華早報：北京對美日宣洩怒氣後 外交面臨兩難 - ETtoday新聞雲",
      "description": "美國眾議院議長裴洛西（Nancy Pelosi）訪台後，中方透過軍事演習展示武力，也對美日兩國宣洩怒氣。分析指出，這對北京政府來說，似乎是加大外交賭注，如今處於兩難困境之中，到底該讓事態進一步升級，或是努力與其他鄰國站在同一陣線，以避免各國疏離。(第四次台海危機,南華早報,軍演)",
      "url": "https://www.ettoday.net/news/20220807/2311244.htm",
      "urlToImage": "https://cdn2.ettoday.net/images/6497/d6497245.jpg",
      "publishedAt": "2022-08-07T09:46:00Z",
      "content": "8\r\nNancy Pelosi\r\n7\r\nSourabh Gupta\r\n4\r\nLa Trobe UniversityNick Bisley\r\nAntony Blinken\r\nLu Xiang\r\nLi Mingjiang"
    },
    {
      "source": { "id": null, "name": "Ltn.com.tw" },
      "author": "自由時報",
      "title": "共軍實彈射擊結束 外籍航空航班已陸續恢復 - 自由時報",
      "description": "中共解放軍4日起在台灣周邊海域舉行實彈演習至今天中午。而中國發布1到6個臨時危險區飛航公告今天中午12時失效，第7區明天上午10時失效。原本這兩天取消外籍航空航班陸續恢復正常。美國眾議院議長裴洛西8月2日晚間至3日傍晚訪台，中國宣布共軍4日中午12時至7日中午12時，在台灣附近6個海域「進行重要軍事演訓行動，並組織實彈射擊」。航港局4日上午再發布新的航船布告，其中提到中共解放軍的軍演區域多了1處，在東部海域。",
      "url": "https://news.ltn.com.tw/news/politics/breakingnews/4017634",
      "urlToImage": "https://img.ltn.com.tw/Upload/news/600/2022/08/07/php4Ha236.jpg",
      "publishedAt": "2022-08-07T10:06:53Z",
      "content": null
    },
    {
      "source": { "id": null, "name": "Appledaily.com.tw" },
      "author": "蘋果新聞網",
      "title": "軍演3天沒完沒了！共軍今宣布「繼續對台灣實戰演訓」 檢驗聯合火力｜蘋果新聞網｜蘋果日報 - 蘋果新聞網",
      "description": "中國解放軍從4日開始大動作舉行 3 天的實彈軍演，而東部戰區按計劃預計是今天（7日）中午12點會結束演習，但是稍早微博「東部戰區」發出快訊表示，「8月7日，中國人民解放軍東部戰區按計劃，繼續位台灣周邊海空域進行實戰化聯合演訓，重點檢驗聯合火力對地打擊和遠距離空中打擊能力」。",
      "url": "https://www.appledaily.com.tw/politics/20220807/253DB510691B1C30237B826459",
      "urlToImage": "https://static.appledaily.com.tw/prod/2022-08/253DB510691B1C30237B826459/5a421a64ce4f93043abbd8137b5828ad_large.jpg",
      "publishedAt": "2022-08-07T10:02:19Z",
      "content": null
    },
    {
      "source": { "id": null, "name": "Ettoday.net" },
      "author": "ETtoday新聞雲",
      "title": "南華早報：北京對美日宣洩怒氣後 外交面臨兩難 - ETtoday新聞雲",
      "description": "美國眾議院議長裴洛西（Nancy Pelosi）訪台後，中方透過軍事演習展示武力，也對美日兩國宣洩怒氣。分析指出，這對北京政府來說，似乎是加大外交賭注，如今處於兩難困境之中，到底該讓事態進一步升級，或是努力與其他鄰國站在同一陣線，以避免各國疏離。(第四次台海危機,南華早報,軍演)",
      "url": "https://www.ettoday.net/news/20220807/2311244.htm",
      "urlToImage": "https://cdn2.ettoday.net/images/6497/d6497245.jpg",
      "publishedAt": "2022-08-07T09:46:00Z",
      "content": "8\r\nNancy Pelosi\r\n7\r\nSourabh Gupta\r\n4\r\nLa Trobe UniversityNick Bisley\r\nAntony Blinken\r\nLu Xiang\r\nLi Mingjiang"
    },
    {
      "source": { "id": null, "name": "Ltn.com.tw" },
      "author": "自由時報",
      "title": "共軍實彈射擊結束 外籍航空航班已陸續恢復 - 自由時報",
      "description": "中共解放軍4日起在台灣周邊海域舉行實彈演習至今天中午。而中國發布1到6個臨時危險區飛航公告今天中午12時失效，第7區明天上午10時失效。原本這兩天取消外籍航空航班陸續恢復正常。美國眾議院議長裴洛西8月2日晚間至3日傍晚訪台，中國宣布共軍4日中午12時至7日中午12時，在台灣附近6個海域「進行重要軍事演訓行動，並組織實彈射擊」。航港局4日上午再發布新的航船布告，其中提到中共解放軍的軍演區域多了1處，在東部海域。",
      "url": "https://news.ltn.com.tw/news/politics/breakingnews/4017634",
      "urlToImage": "https://img.ltn.com.tw/Upload/news/600/2022/08/07/php4Ha236.jpg",
      "publishedAt": "2022-08-07T10:06:53Z",
      "content": null
    },
    {
      "source": { "id": null, "name": "Appledaily.com.tw" },
      "author": "蘋果新聞網",
      "title": "軍演3天沒完沒了！共軍今宣布「繼續對台灣實戰演訓」 檢驗聯合火力｜蘋果新聞網｜蘋果日報 - 蘋果新聞網",
      "description": "中國解放軍從4日開始大動作舉行 3 天的實彈軍演，而東部戰區按計劃預計是今天（7日）中午12點會結束演習，但是稍早微博「東部戰區」發出快訊表示，「8月7日，中國人民解放軍東部戰區按計劃，繼續位台灣周邊海空域進行實戰化聯合演訓，重點檢驗聯合火力對地打擊和遠距離空中打擊能力」。",
      "url": "https://www.appledaily.com.tw/politics/20220807/253DB510691B1C30237B826459",
      "urlToImage": "https://static.appledaily.com.tw/prod/2022-08/253DB510691B1C30237B826459/5a421a64ce4f93043abbd8137b5828ad_large.jpg",
      "publishedAt": "2022-08-07T10:02:19Z",
      "content": null
    },
    {
      "source": { "id": null, "name": "Ettoday.net" },
      "author": "ETtoday新聞雲",
      "title": "南華早報：北京對美日宣洩怒氣後 外交面臨兩難 - ETtoday新聞雲",
      "description": "美國眾議院議長裴洛西（Nancy Pelosi）訪台後，中方透過軍事演習展示武力，也對美日兩國宣洩怒氣。分析指出，這對北京政府來說，似乎是加大外交賭注，如今處於兩難困境之中，到底該讓事態進一步升級，或是努力與其他鄰國站在同一陣線，以避免各國疏離。(第四次台海危機,南華早報,軍演)",
      "url": "https://www.ettoday.net/news/20220807/2311244.htm",
      "urlToImage": "https://cdn2.ettoday.net/images/6497/d6497245.jpg",
      "publishedAt": "2022-08-07T09:46:00Z",
      "content": "8\r\nNancy Pelosi\r\n7\r\nSourabh Gupta\r\n4\r\nLa Trobe UniversityNick Bisley\r\nAntony Blinken\r\nLu Xiang\r\nLi Mingjiang"
    },
    {
      "source": { "id": null, "name": "Ltn.com.tw" },
      "author": "自由時報",
      "title": "共軍實彈射擊結束 外籍航空航班已陸續恢復 - 自由時報",
      "description": "中共解放軍4日起在台灣周邊海域舉行實彈演習至今天中午。而中國發布1到6個臨時危險區飛航公告今天中午12時失效，第7區明天上午10時失效。原本這兩天取消外籍航空航班陸續恢復正常。美國眾議院議長裴洛西8月2日晚間至3日傍晚訪台，中國宣布共軍4日中午12時至7日中午12時，在台灣附近6個海域「進行重要軍事演訓行動，並組織實彈射擊」。航港局4日上午再發布新的航船布告，其中提到中共解放軍的軍演區域多了1處，在東部海域。",
      "url": "https://news.ltn.com.tw/news/politics/breakingnews/4017634",
      "urlToImage": "https://img.ltn.com.tw/Upload/news/600/2022/08/07/php4Ha236.jpg",
      "publishedAt": "2022-08-07T10:06:53Z",
      "content": null
    },
    {
      "source": { "id": null, "name": "Appledaily.com.tw" },
      "author": "蘋果新聞網",
      "title": "軍演3天沒完沒了！共軍今宣布「繼續對台灣實戰演訓」 檢驗聯合火力｜蘋果新聞網｜蘋果日報 - 蘋果新聞網",
      "description": "中國解放軍從4日開始大動作舉行 3 天的實彈軍演，而東部戰區按計劃預計是今天（7日）中午12點會結束演習，但是稍早微博「東部戰區」發出快訊表示，「8月7日，中國人民解放軍東部戰區按計劃，繼續位台灣周邊海空域進行實戰化聯合演訓，重點檢驗聯合火力對地打擊和遠距離空中打擊能力」。",
      "url": "https://www.appledaily.com.tw/politics/20220807/253DB510691B1C30237B826459",
      "urlToImage": "https://static.appledaily.com.tw/prod/2022-08/253DB510691B1C30237B826459/5a421a64ce4f93043abbd8137b5828ad_large.jpg",
      "publishedAt": "2022-08-07T10:02:19Z",
      "content": null
    },
    {
      "source": { "id": null, "name": "Ettoday.net" },
      "author": "ETtoday新聞雲",
      "title": "南華早報：北京對美日宣洩怒氣後 外交面臨兩難 - ETtoday新聞雲",
      "description": "美國眾議院議長裴洛西（Nancy Pelosi）訪台後，中方透過軍事演習展示武力，也對美日兩國宣洩怒氣。分析指出，這對北京政府來說，似乎是加大外交賭注，如今處於兩難困境之中，到底該讓事態進一步升級，或是努力與其他鄰國站在同一陣線，以避免各國疏離。(第四次台海危機,南華早報,軍演)",
      "url": "https://www.ettoday.net/news/20220807/2311244.htm",
      "urlToImage": "https://cdn2.ettoday.net/images/6497/d6497245.jpg",
      "publishedAt": "2022-08-07T09:46:00Z",
      "content": "8\r\nNancy Pelosi\r\n7\r\nSourabh Gupta\r\n4\r\nLa Trobe UniversityNick Bisley\r\nAntony Blinken\r\nLu Xiang\r\nLi Mingjiang"
    }
  ]
}
